fpga/hdl/fmcw_defines.vh
`define FMCW_DEFAULT_PARAMS parameter \
NTAPS = 120, \
CntW = 7, \
TW = 16, \
IW = 12, \
OW = 16, \
IntW = 29, \
USBDW = 8, \
SDDW = 4, \
GPIOW = 6, \
M = 20, \
MW = 5

fpga/hdl/adf4158.v
`default_nettype none

`include "fmcw_defines.vh"

module adf4158 #( `FMCW_DEFAULT_PARAMS )
        (
         input wire  clk_i, /* 40MHz reference clock. */
         output reg  ce_o, /* Low voltage powers down device. */
         output reg  le_o, /* Low when writing data and pull high to flush to internal registers. */
         output reg  clk_o, /* 20MHz. Synchronizes data loaded into configuration registers. */
         input wire  muxout_i,
         output reg  txdata_o,
         output wire data_o /* Configuration registers data. */
         );

        initial begin
                ce_o = 1'b1;
                le_o = 1'b1;
                clk_o = 1'b0;
                txdata_o = 1'b0;
        end

        assign data_o = (!le_o) ? r[reg_cnt-1][bit_cnt] : 1'b0;

        /* Configuration registers.
         *  Initialization sequence: r7, r6_0, r6_1, r5_0, r5_1, r4, r3, r2, r1, r0
         */
        reg [31:0] r [0:9];

        initial begin
                r[0] = {1'd1, 4'd15, 12'd265, 12'd0, 3'd0};
                r[1] = {4'd0, 13'd0, 12'd0, 3'd1};
                r[2] = {3'd0, 1'd1, 4'd0, 1'd0, 1'd1, 1'd1, 1'd0, 5'd1, 12'd10, 3'd2};
                r[3] = {16'd0, 1'd0, 1'd0, 2'd0, 2'd0, 1'd0, 1'd0, 1'd0, 1'd1, 1'd0, 1'd0, 1'd0, 3'd3};
                r[4] = {1'd0, 5'd0, 1'd0, 2'd0, 2'd3, 2'd3, 12'd1, 4'd0, 3'd4};
                r[5] = {2'd0, 1'd0, 1'd0, 2'd0, 1'd0, 1'd0, 1'd1, 4'd4, 16'd31457, 3'd5};
                r[6] = {2'd0, 1'd0, 1'd0, 2'd0, 1'd0, 1'd0, 1'd0, 4'd4, 16'd31457, 3'd5};
                r[7] = {8'd0, 1'd1, 20'd2000, 3'd6};
                r[8] = {8'd0, 1'd0, 20'd2000, 3'd6};
                r[9] = {13'd0, 1'd0, 1'd1, 1'd1, 1'd0, 12'd4000, 3'd7};
        end

        localparam num_regs = 10;
        reg [3:0]  reg_cnt = 4'd10;
        reg [4:0]  bit_cnt = 5'd31;
        wire       done = (reg_cnt == 4'd0) ? 1'b1 : 1'b0;
        reg        delay = 1'b0;

        always @(posedge clk_i) begin
                if (!done && !delay) begin
                        le_o <= 1'b0;
                end
                else begin
                        le_o <= 1'b1;
                end

                if (!le_o) begin
                        clk_o <= !clk_o;
                end
                else begin
                        clk_o <= 1'b0;
                end

                if (bit_cnt == 5'd0) begin
                        delay <= 1'b1;
                end
                else begin
                        delay <= 1'b0;
                end
        end

        always @(negedge clk_o) begin
                if (!le_o) begin
                        bit_cnt <= bit_cnt - 5'd1;
                        reg_cnt <= reg_cnt;
                end
                else begin
                        bit_cnt <= 5'd31;
                        reg_cnt <= reg_cnt - 4'd1;
                end
        end

endmodule // adf4158

fpga/hdl/tb/adf4158_tb.v
`default_nettype none

`include "../fmcw_defines.vh"
`include "../adf4158.v"

`timescale 100ps/100ps
module adf4158_tb;

        reg clk = 1'b0;
        wire ce;
        wire le;
        wire clk_adf;
        wire txdata;
        wire data;

        initial begin
                $dumpfile("adf4158.vcd");
                $dumpvars(0, adf4158_tb);

                #1000000 $finish;
        end

        always #125 clk = !clk;

        adf4158 adf4158 (.clk_i(clk),
                         .ce_o(ce),
                         .le_o(le),
                         .clk_o(clk_adf),
                         .txdata_o(txdata),
                         .data_o(data));

endmodule // adf4158_tb

fpga/hdl/tb/adf4158.vcd
$date
	Sat Feb  9 10:14:11 2019
$end
$version
	Icarus Verilog
$end
$timescale
	100ps
$end
$scope module adf4158_tb $end
$var wire 1 ! txdata $end
$var wire 1 " le $end
$var wire 1 # data $end
$var wire 1 $ clk_adf $end
$var wire 1 % ce $end
$var reg 1 & clk $end
$scope module adf4158 $end
$var wire 1 & clk_i $end
$var wire 1 ' muxout_i $end
$var wire 1 ( done $end
$var wire 1 # data_o $end
$var reg 5 ) bit_cnt [4:0] $end
$var reg 1 % ce_o $end
$var reg 1 $ clk_o $end
$var reg 1 * delay $end
$var reg 1 " le_o $end
$var reg 4 + reg_cnt [3:0] $end
$var reg 1 ! txdata_o $end
$upscope $end
$upscope $end
$enddefinitions $end
#0
$dumpvars
b1010 +
0*
b11111 )
0(
z'
0&
1%
0$
0#
1"
0!
$end
#125
0"
1&
#250
0&
#375
1$
1&
#500
0&
#625
b11110 )
0$
1&
#750
0&
#875
1$
1&
#1000
0&
#1125
b11101 )
0$
1&
#1250
0&
#1375
1$
1&
#1500
0&
#1625
b11100 )
0$
1&
#1750
0&
#1875
1$
1&
#2000
0&
#2125
b11011 )
0$
1&
#2250
0&
#2375
1$
1&
#2500
0&
#2625
b11010 )
0$
1&
#2750
0&
#2875
1$
1&
#3000
0&
#3125
b11001 )
0$
1&
#3250
0&
#3375
1$
1&
#3500
0&
#3625
b11000 )
0$
1&
#3750
0&
#3875
1$
1&
#4000
0&
#4125
b10111 )
0$
1&
#4250
0&
#4375
1$
1&
#4500
0&
#4625
b10110 )
0$
1&
#4750
0&
#4875
1$
1&
#5000
0&
#5125
b10101 )
0$
1&
#5250
0&
#5375
1$
1&
#5500
0&
#5625
b10100 )
0$
1&
#5750
0&
#5875
1$
1&
#6000
0&
#6125
b10011 )
0$
1&
#6250
0&
#6375
1$
1&
#6500
0&
#6625
b10010 )
0$
1&
#6750
0&
#6875
1$
1&
#7000
0&
#7125
1#
b10001 )
0$
1&
#7250
0&
#7375
1$
1&
#7500
0&
#7625
b10000 )
0$
1&
#7750
0&
#7875
1$
1&
#8000
0&
#8125
0#
b1111 )
0$
1&
#8250
0&
#8375
1$
1&
#8500
0&
#8625
1#
b1110 )
0$
1&
#8750
0&
#8875
1$
1&
#9000
0&
#9125
b1101 )
0$
1&
#9250
0&
#9375
1$
1&
#9500
0&
#9625
b1100 )
0$
1&
#9750
0&
#9875
1$
1&
#10000
0&
#10125
b1011 )
0$
1&
#10250
0&
#10375
1$
1&
#10500
0&
#10625
b1010 )
0$
1&
#10750
0&
#10875
1$
1&
#11000
0&
#11125
0#
b1001 )
0$
1&
#11250
0&
#11375
1$
1&
#11500
0&
#11625
1#
b1000 )
0$
1&
#11750
0&
#11875
1$
1&
#12000
0&
#12125
0#
b111 )
0$
1&
#12250
0&
#12375
1$
1&
#12500
0&
#12625
b110 )
0$
1&
#12750
0&
#12875
1$
1&
#13000
0&
#13125
b101 )
0$
1&
#13250
0&
#13375
1$
1&
#13500
0&
#13625
b100 )
0$
1&
#13750
0&
#13875
1$
1&
#14000
0&
#14125
b11 )
0$
1&
#14250
0&
#14375
1$
1&
#14500
0&
#14625
1#
b10 )
0$
1&
#14750
0&
#14875
1$
1&
#15000
0&
#15125
b1 )
0$
1&
#15250
0&
#15375
1$
1&
#15500
0&
#15625
b0 )
0$
1&
#15750
0&
#15875
1*
1$
1&
#16000
0&
#16125
b1001 +
b11111 )
0#
0$
1"
1&
#16250
0&
#16375
0*
1&
#16500
0&
#16625
0"
1&
#16750
0&
#16875
1$
1&
#17000
0&
#17125
b11110 )
0$
1&
#17250
0&
#17375
1$
1&
#17500
0&
#17625
b11101 )
0$
1&
#17750
0&
#17875
1$
1&
#18000
0&
#18125
b11100 )
0$
1&
#18250
0&
#18375
1$
1&
#18500
0&
#18625
b11011 )
0$
1&
#18750
0&
#18875
1$
1&
#19000
0&
#19125
b11010 )
0$
1&
#19250
0&
#19375
1$
1&
#19500
0&
#19625
b11001 )
0$
1&
#19750
0&
#19875
1$
1&
#20000
0&
#20125
b11000 )
0$
1&
#20250
0&
#20375
1$
1&
#20500
0&
#20625
b10111 )
0$
1&
#20750
0&
#20875
1$
1&
#21000
0&
#21125
b10110 )
0$
1&
#21250
0&
#21375
1$
1&
#21500
0&
#21625
b10101 )
0$
1&
#21750
0&
#21875
1$
1&
#22000
0&
#22125
b10100 )
0$
1&
#22250
0&
#22375
1$
1&
#22500
0&
#22625
b10011 )
0$
1&
#22750
0&
#22875
1$
1&
#23000
0&
#23125
b10010 )
0$
1&
#23250
0&
#23375
1$
1&
#23500
0&
#23625
b10001 )
0$
1&
#23750
0&
#23875
1$
1&
#24000
0&
#24125
b10000 )
0$
1&
#24250
0&
#24375
1$
1&
#24500
0&
#24625
b1111 )
0$
1&
#24750
0&
#24875
1$
1&
#25000
0&
#25125
b1110 )
0$
1&
#25250
0&
#25375
1$
1&
#25500
0&
#25625
1#
b1101 )
0$
1&
#25750
0&
#25875
1$
1&
#26000
0&
#26125
b1100 )
0$
1&
#26250
0&
#26375
1$
1&
#26500
0&
#26625
b1011 )
0$
1&
#26750
0&
#26875
1$
1&
#27000
0&
#27125
b1010 )
0$
1&
#27250
0&
#27375
1$
1&
#27500
0&
#27625
b1001 )
0$
1&
#27750
0&
#27875
1$
1&
#28000
0&
#28125
0#
b1000 )
0$
1&
#28250
0&
#28375
1$
1&
#28500
0&
#28625
1#
b111 )
0$
1&
#28750
0&
#28875
1$
1&
#29000
0&
#29125
0#
b110 )
0$
1&
#29250
0&
#29375
1$
1&
#29500
0&
#29625
b101 )
0$
1&
#29750
0&
#29875
1$
1&
#30000
0&
#30125
b100 )
0$
1&
#30250
0&
#30375
1$
1&
#30500
0&
#30625
b11 )
0$
1&
#30750
0&
#30875
1$
1&
#31000
0&
#31125
1#
b10 )
0$
1&
#31250
0&
#31375
1$
1&
#31500
0&
#31625
b1 )
0$
1&
#31750
0&
#31875
1$
1&
#32000
0&
#32125
0#
b0 )
0$
1&
#32250
0&
#32375
1*
1$
1&
#32500
0&
#32625
b1000 +
b11111 )
0$
1"
1&
#32750
0&
#32875
0*
1&
#33000
0&
#33125
0"
1&
#33250
0&
#33375
1$
1&
#33500
0&
#33625
b11110 )
0$
1&
#33750
0&
#33875
1$
1&
#34000
0&
#34125
b11101 )
0$
1&
#34250
0&
#34375
1$
1&
#34500
0&
#34625
b11100 )
0$
1&
#34750
0&
#34875
1$
1&
#35000
0&
#35125
b11011 )
0$
1&
#35250
0&
#35375
1$
1&
#35500
0&
#35625
b11010 )
0$
1&
#35750
0&
#35875
1$
1&
#36000
0&
#36125
b11001 )
0$
1&
#36250
0&
#36375
1$
1&
#36500
0&
#36625
b11000 )
0$
1&
#36750
0&
#36875
1$
1&
#37000
0&
#37125
1#
b10111 )
0$
1&
#37250
0&
#37375
1$
1&
#37500
0&
#37625
0#
b10110 )
0$
1&
#37750
0&
#37875
1$
1&
#38000
0&
#38125
b10101 )
0$
1&
#38250
0&
#38375
1$
1&
#38500
0&
#38625
b10100 )
0$
1&
#38750
0&
#38875
1$
1&
#39000
0&
#39125
b10011 )
0$
1&
#39250
0&
#39375
1$
1&
#39500
0&
#39625
b10010 )
0$
1&
#39750
0&
#39875
1$
1&
#40000
0&
#40125
b10001 )
0$
1&
#40250
0&
#40375
1$
1&
#40500
0&
#40625
b10000 )
0$
1&
#40750
0&
#40875
1$
1&
#41000
0&
#41125
b1111 )
0$
1&
#41250
0&
#41375
1$
1&
#41500
0&
#41625
b1110 )
0$
1&
#41750
0&
#41875
1$
1&
#42000
0&
#42125
1#
b1101 )
0$
1&
#42250
0&
#42375
1$
1&
#42500
0&
#42625
b1100 )
0$
1&
#42750
0&
#42875
1$
1&
#43000
0&
#43125
b1011 )
0$
1&
#43250
0&
#43375
1$
1&
#43500
0&
#43625
b1010 )
0$
1&
#43750
0&
#43875
1$
1&
#44000
0&
#44125
b1001 )
0$
1&
#44250
0&
#44375
1$
1&
#44500
0&
#44625
0#
b1000 )
0$
1&
#44750
0&
#44875
1$
1&
#45000
0&
#45125
1#
b111 )
0$
1&
#45250
0&
#45375
1$
1&
#45500
0&
#45625
0#
b110 )
0$
1&
#45750
0&
#45875
1$
1&
#46000
0&
#46125
b101 )
0$
1&
#46250
0&
#46375
1$
1&
#46500
0&
#46625
b100 )
0$
1&
#46750
0&
#46875
1$
1&
#47000
0&
#47125
b11 )
0$
1&
#47250
0&
#47375
1$
1&
#47500
0&
#47625
1#
b10 )
0$
1&
#47750
0&
#47875
1$
1&
#48000
0&
#48125
b1 )
0$
1&
#48250
0&
#48375
1$
1&
#48500
0&
#48625
0#
b0 )
0$
1&
#48750
0&
#48875
1*
1$
1&
#49000
0&
#49125
b111 +
b11111 )
0$
1"
1&
#49250
0&
#49375
0*
1&
#49500
0&
#49625
0"
1&
#49750
0&
#49875
1$
1&
#50000
0&
#50125
b11110 )
0$
1&
#50250
0&
#50375
1$
1&
#50500
0&
#50625
b11101 )
0$
1&
#50750
0&
#50875
1$
1&
#51000
0&
#51125
b11100 )
0$
1&
#51250
0&
#51375
1$
1&
#51500
0&
#51625
b11011 )
0$
1&
#51750
0&
#51875
1$
1&
#52000
0&
#52125
b11010 )
0$
1&
#52250
0&
#52375
1$
1&
#52500
0&
#52625
b11001 )
0$
1&
#52750
0&
#52875
1$
1&
#53000
0&
#53125
b11000 )
0$
1&
#53250
0&
#53375
1$
1&
#53500
0&
#53625
b10111 )
0$
1&
#53750
0&
#53875
1$
1&
#54000
0&
#54125
b10110 )
0$
1&
#54250
0&
#54375
1$
1&
#54500
0&
#54625
1#
b10101 )
0$
1&
#54750
0&
#54875
1$
1&
#55000
0&
#55125
0#
b10100 )
0$
1&
#55250
0&
#55375
1$
1&
#55500
0&
#55625
b10011 )
0$
1&
#55750
0&
#55875
1$
1&
#56000
0&
#56125
b10010 )
0$
1&
#56250
0&
#56375
1$
1&
#56500
0&
#56625
1#
b10001 )
0$
1&
#56750
0&
#56875
1$
1&
#57000
0&
#57125
b10000 )
0$
1&
#57250
0&
#57375
1$
1&
#57500
0&
#57625
b1111 )
0$
1&
#57750
0&
#57875
1$
1&
#58000
0&
#58125
b1110 )
0$
1&
#58250
0&
#58375
1$
1&
#58500
0&
#58625
0#
b1101 )
0$
1&
#58750
0&
#58875
1$
1&
#59000
0&
#59125
1#
b1100 )
0$
1&
#59250
0&
#59375
1$
1&
#59500
0&
#59625
0#
b1011 )
0$
1&
#59750
0&
#59875
1$
1&
#60000
0&
#60125
1#
b1010 )
0$
1&
#60250
0&
#60375
1$
1&
#60500
0&
#60625
b1001 )
0$
1&
#60750
0&
#60875
1$
1&
#61000
0&
#61125
b1000 )
0$
1&
#61250
0&
#61375
1$
1&
#61500
0&
#61625
0#
b111 )
0$
1&
#61750
0&
#61875
1$
1&
#62000
0&
#62125
b110 )
0$
1&
#62250
0&
#62375
1$
1&
#62500
0&
#62625
b101 )
0$
1&
#62750
0&
#62875
1$
1&
#63000
0&
#63125
b100 )
0$
1&
#63250
0&
#63375
1$
1&
#63500
0&
#63625
1#
b11 )
0$
1&
#63750
0&
#63875
1$
1&
#64000
0&
#64125
b10 )
0$
1&
#64250
0&
#64375
1$
1&
#64500
0&
#64625
0#
b1 )
0$
1&
#64750
0&
#64875
1$
1&
#65000
0&
#65125
1#
b0 )
0$
1&
#65250
0&
#65375
1*
1$
1&
#65500
0&
#65625
b110 +
b11111 )
0#
0$
1"
1&
#65750
0&
#65875
0*
1&
#66000
0&
#66125
0"
1&
#66250
0&
#66375
1$
1&
#66500
0&
#66625
b11110 )
0$
1&
#66750
0&
#66875
1$
1&
#67000
0&
#67125
b11101 )
0$
1&
#67250
0&
#67375
1$
1&
#67500
0&
#67625
b11100 )
0$
1&
#67750
0&
#67875
1$
1&
#68000
0&
#68125
b11011 )
0$
1&
#68250
0&
#68375
1$
1&
#68500
0&
#68625
b11010 )
0$
1&
#68750
0&
#68875
1$
1&
#69000
0&
#69125
b11001 )
0$
1&
#69250
0&
#69375
1$
1&
#69500
0&
#69625
b11000 )
0$
1&
#69750
0&
#69875
1$
1&
#70000
0&
#70125
1#
b10111 )
0$
1&
#70250
0&
#70375
1$
1&
#70500
0&
#70625
0#
b10110 )
0$
1&
#70750
0&
#70875
1$
1&
#71000
0&
#71125
1#
b10101 )
0$
1&
#71250
0&
#71375
1$
1&
#71500
0&
#71625
0#
b10100 )
0$
1&
#71750
0&
#71875
1$
1&
#72000
0&
#72125
b10011 )
0$
1&
#72250
0&
#72375
1$
1&
#72500
0&
#72625
b10010 )
0$
1&
#72750
0&
#72875
1$
1&
#73000
0&
#73125
1#
b10001 )
0$
1&
#73250
0&
#73375
1$
1&
#73500
0&
#73625
b10000 )
0$
1&
#73750
0&
#73875
1$
1&
#74000
0&
#74125
b1111 )
0$
1&
#74250
0&
#74375
1$
1&
#74500
0&
#74625
b1110 )
0$
1&
#74750
0&
#74875
1$
1&
#75000
0&
#75125
0#
b1101 )
0$
1&
#75250
0&
#75375
1$
1&
#75500
0&
#75625
1#
b1100 )
0$
1&
#75750
0&
#75875
1$
1&
#76000
0&
#76125
0#
b1011 )
0$
1&
#76250
0&
#76375
1$
1&
#76500
0&
#76625
1#
b1010 )
0$
1&
#76750
0&
#76875
1$
1&
#77000
0&
#77125
b1001 )
0$
1&
#77250
0&
#77375
1$
1&
#77500
0&
#77625
b1000 )
0$
1&
#77750
0&
#77875
1$
1&
#78000
0&
#78125
0#
b111 )
0$
1&
#78250
0&
#78375
1$
1&
#78500
0&
#78625
b110 )
0$
1&
#78750
0&
#78875
1$
1&
#79000
0&
#79125
b101 )
0$
1&
#79250
0&
#79375
1$
1&
#79500
0&
#79625
b100 )
0$
1&
#79750
0&
#79875
1$
1&
#80000
0&
#80125
1#
b11 )
0$
1&
#80250
0&
#80375
1$
1&
#80500
0&
#80625
b10 )
0$
1&
#80750
0&
#80875
1$
1&
#81000
0&
#81125
0#
b1 )
0$
1&
#81250
0&
#81375
1$
1&
#81500
0&
#81625
1#
b0 )
0$
1&
#81750
0&
#81875
1*
1$
1&
#82000
0&
#82125
b101 +
b11111 )
0#
0$
1"
1&
#82250
0&
#82375
0*
1&
#82500
0&
#82625
0"
1&
#82750
0&
#82875
1$
1&
#83000
0&
#83125
b11110 )
0$
1&
#83250
0&
#83375
1$
1&
#83500
0&
#83625
b11101 )
0$
1&
#83750
0&
#83875
1$
1&
#84000
0&
#84125
b11100 )
0$
1&
#84250
0&
#84375
1$
1&
#84500
0&
#84625
b11011 )
0$
1&
#84750
0&
#84875
1$
1&
#85000
0&
#85125
b11010 )
0$
1&
#85250
0&
#85375
1$
1&
#85500
0&
#85625
b11001 )
0$
1&
#85750
0&
#85875
1$
1&
#86000
0&
#86125
b11000 )
0$
1&
#86250
0&
#86375
1$
1&
#86500
0&
#86625
b10111 )
0$
1&
#86750
0&
#86875
1$
1&
#87000
0&
#87125
1#
b10110 )
0$
1&
#87250
0&
#87375
1$
1&
#87500
0&
#87625
b10101 )
0$
1&
#87750
0&
#87875
1$
1&
#88000
0&
#88125
b10100 )
0$
1&
#88250
0&
#88375
1$
1&
#88500
0&
#88625
b10011 )
0$
1&
#88750
0&
#88875
1$
1&
#89000
0&
#89125
0#
b10010 )
0$
1&
#89250
0&
#89375
1$
1&
#89500
0&
#89625
b10001 )
0$
1&
#89750
0&
#89875
1$
1&
#90000
0&
#90125
b10000 )
0$
1&
#90250
0&
#90375
1$
1&
#90500
0&
#90625
b1111 )
0$
1&
#90750
0&
#90875
1$
1&
#91000
0&
#91125
b1110 )
0$
1&
#91250
0&
#91375
1$
1&
#91500
0&
#91625
b1101 )
0$
1&
#91750
0&
#91875
1$
1&
#92000
0&
#92125
b1100 )
0$
1&
#92250
0&
#92375
1$
1&
#92500
0&
#92625
b1011 )
0$
1&
#92750
0&
#92875
1$
1&
#93000
0&
#93125
b1010 )
0$
1&
#93250
0&
#93375
1$
1&
#93500
0&
#93625
b1001 )
0$
1&
#93750
0&
#93875
1$
1&
#94000
0&
#94125
b1000 )
0$
1&
#94250
0&
#94375
1$
1&
#94500
0&
#94625
1#
b111 )
0$
1&
#94750
0&
#94875
1$
1&
#95000
0&
#95125
0#
b110 )
0$
1&
#95250
0&
#95375
1$
1&
#95500
0&
#95625
b101 )
0$
1&
#95750
0&
#95875
1$
1&
#96000
0&
#96125
b100 )
0$
1&
#96250
0&
#96375
1$
1&
#96500
0&
#96625
b11 )
0$
1&
#96750
0&
#96875
1$
1&
#97000
0&
#97125
1#
b10 )
0$
1&
#97250
0&
#97375
1$
1&
#97500
0&
#97625
0#
b1 )
0$
1&
#97750
0&
#97875
1$
1&
#98000
0&
#98125
b0 )
0$
1&
#98250
0&
#98375
1*
1$
1&
#98500
0&
#98625
b100 +
b11111 )
0$
1"
1&
#98750
0&
#98875
0*
1&
#99000
0&
#99125
0"
1&
#99250
0&
#99375
1$
1&
#99500
0&
#99625
b11110 )
0$
1&
#99750
0&
#99875
1$
1&
#100000
0&
#100125
b11101 )
0$
1&
#100250
0&
#100375
1$
1&
#100500
0&
#100625
b11100 )
0$
1&
#100750
0&
#100875
1$
1&
#101000
0&
#101125
b11011 )
0$
1&
#101250
0&
#101375
1$
1&
#101500
0&
#101625
b11010 )
0$
1&
#101750
0&
#101875
1$
1&
#102000
0&
#102125
b11001 )
0$
1&
#102250
0&
#102375
1$
1&
#102500
0&
#102625
b11000 )
0$
1&
#102750
0&
#102875
1$
1&
#103000
0&
#103125
b10111 )
0$
1&
#103250
0&
#103375
1$
1&
#103500
0&
#103625
b10110 )
0$
1&
#103750
0&
#103875
1$
1&
#104000
0&
#104125
b10101 )
0$
1&
#104250
0&
#104375
1$
1&
#104500
0&
#104625
b10100 )
0$
1&
#104750
0&
#104875
1$
1&
#105000
0&
#105125
b10011 )
0$
1&
#105250
0&
#105375
1$
1&
#105500
0&
#105625
b10010 )
0$
1&
#105750
0&
#105875
1$
1&
#106000
0&
#106125
b10001 )
0$
1&
#106250
0&
#106375
1$
1&
#106500
0&
#106625
b10000 )
0$
1&
#106750
0&
#106875
1$
1&
#107000
0&
#107125
b1111 )
0$
1&
#107250
0&
#107375
1$
1&
#107500
0&
#107625
b1110 )
0$
1&
#107750
0&
#107875
1$
1&
#108000
0&
#108125
b1101 )
0$
1&
#108250
0&
#108375
1$
1&
#108500
0&
#108625
b1100 )
0$
1&
#108750
0&
#108875
1$
1&
#109000
0&
#109125
b1011 )
0$
1&
#109250
0&
#109375
1$
1&
#109500
0&
#109625
b1010 )
0$
1&
#109750
0&
#109875
1$
1&
#110000
0&
#110125
b1001 )
0$
1&
#110250
0&
#110375
1$
1&
#110500
0&
#110625
b1000 )
0$
1&
#110750
0&
#110875
1$
1&
#111000
0&
#111125
b111 )
0$
1&
#111250
0&
#111375
1$
1&
#111500
0&
#111625
1#
b110 )
0$
1&
#111750
0&
#111875
1$
1&
#112000
0&
#112125
0#
b101 )
0$
1&
#112250
0&
#112375
1$
1&
#112500
0&
#112625
b100 )
0$
1&
#112750
0&
#112875
1$
1&
#113000
0&
#113125
b11 )
0$
1&
#113250
0&
#113375
1$
1&
#113500
0&
#113625
b10 )
0$
1&
#113750
0&
#113875
1$
1&
#114000
0&
#114125
1#
b1 )
0$
1&
#114250
0&
#114375
1$
1&
#114500
0&
#114625
b0 )
0$
1&
#114750
0&
#114875
1*
1$
1&
#115000
0&
#115125
b11 +
b11111 )
0#
0$
1"
1&
#115250
0&
#115375
0*
1&
#115500
0&
#115625
0"
1&
#115750
0&
#115875
1$
1&
#116000
0&
#116125
b11110 )
0$
1&
#116250
0&
#116375
1$
1&
#116500
0&
#116625
b11101 )
0$
1&
#116750
0&
#116875
1$
1&
#117000
0&
#117125
1#
b11100 )
0$
1&
#117250
0&
#117375
1$
1&
#117500
0&
#117625
0#
b11011 )
0$
1&
#117750
0&
#117875
1$
1&
#118000
0&
#118125
b11010 )
0$
1&
#118250
0&
#118375
1$
1&
#118500
0&
#118625
b11001 )
0$
1&
#118750
0&
#118875
1$
1&
#119000
0&
#119125
b11000 )
0$
1&
#119250
0&
#119375
1$
1&
#119500
0&
#119625
b10111 )
0$
1&
#119750
0&
#119875
1$
1&
#120000
0&
#120125
1#
b10110 )
0$
1&
#120250
0&
#120375
1$
1&
#120500
0&
#120625
b10101 )
0$
1&
#120750
0&
#120875
1$
1&
#121000
0&
#121125
0#
b10100 )
0$
1&
#121250
0&
#121375
1$
1&
#121500
0&
#121625
b10011 )
0$
1&
#121750
0&
#121875
1$
1&
#122000
0&
#122125
b10010 )
0$
1&
#122250
0&
#122375
1$
1&
#122500
0&
#122625
b10001 )
0$
1&
#122750
0&
#122875
1$
1&
#123000
0&
#123125
b10000 )
0$
1&
#123250
0&
#123375
1$
1&
#123500
0&
#123625
1#
b1111 )
0$
1&
#123750
0&
#123875
1$
1&
#124000
0&
#124125
0#
b1110 )
0$
1&
#124250
0&
#124375
1$
1&
#124500
0&
#124625
b1101 )
0$
1&
#124750
0&
#124875
1$
1&
#125000
0&
#125125
b1100 )
0$
1&
#125250
0&
#125375
1$
1&
#125500
0&
#125625
b1011 )
0$
1&
#125750
0&
#125875
1$
1&
#126000
0&
#126125
b1010 )
0$
1&
#126250
0&
#126375
1$
1&
#126500
0&
#126625
b1001 )
0$
1&
#126750
0&
#126875
1$
1&
#127000
0&
#127125
b1000 )
0$
1&
#127250
0&
#127375
1$
1&
#127500
0&
#127625
b111 )
0$
1&
#127750
0&
#127875
1$
1&
#128000
0&
#128125
1#
b110 )
0$
1&
#128250
0&
#128375
1$
1&
#128500
0&
#128625
0#
b101 )
0$
1&
#128750
0&
#128875
1$
1&
#129000
0&
#129125
1#
b100 )
0$
1&
#129250
0&
#129375
1$
1&
#129500
0&
#129625
0#
b11 )
0$
1&
#129750
0&
#129875
1$
1&
#130000
0&
#130125
b10 )
0$
1&
#130250
0&
#130375
1$
1&
#130500
0&
#130625
1#
b1 )
0$
1&
#130750
0&
#130875
1$
1&
#131000
0&
#131125
0#
b0 )
0$
1&
#131250
0&
#131375
1*
1$
1&
#131500
0&
#131625
b10 +
b11111 )
0$
1"
1&
#131750
0&
#131875
0*
1&
#132000
0&
#132125
0"
1&
#132250
0&
#132375
1$
1&
#132500
0&
#132625
b11110 )
0$
1&
#132750
0&
#132875
1$
1&
#133000
0&
#133125
b11101 )
0$
1&
#133250
0&
#133375
1$
1&
#133500
0&
#133625
b11100 )
0$
1&
#133750
0&
#133875
1$
1&
#134000
0&
#134125
b11011 )
0$
1&
#134250
0&
#134375
1$
1&
#134500
0&
#134625
b11010 )
0$
1&
#134750
0&
#134875
1$
1&
#135000
0&
#135125
b11001 )
0$
1&
#135250
0&
#135375
1$
1&
#135500
0&
#135625
b11000 )
0$
1&
#135750
0&
#135875
1$
1&
#136000
0&
#136125
b10111 )
0$
1&
#136250
0&
#136375
1$
1&
#136500
0&
#136625
b10110 )
0$
1&
#136750
0&
#136875
1$
1&
#137000
0&
#137125
b10101 )
0$
1&
#137250
0&
#137375
1$
1&
#137500
0&
#137625
b10100 )
0$
1&
#137750
0&
#137875
1$
1&
#138000
0&
#138125
b10011 )
0$
1&
#138250
0&
#138375
1$
1&
#138500
0&
#138625
b10010 )
0$
1&
#138750
0&
#138875
1$
1&
#139000
0&
#139125
b10001 )
0$
1&
#139250
0&
#139375
1$
1&
#139500
0&
#139625
b10000 )
0$
1&
#139750
0&
#139875
1$
1&
#140000
0&
#140125
b1111 )
0$
1&
#140250
0&
#140375
1$
1&
#140500
0&
#140625
b1110 )
0$
1&
#140750
0&
#140875
1$
1&
#141000
0&
#141125
b1101 )
0$
1&
#141250
0&
#141375
1$
1&
#141500
0&
#141625
b1100 )
0$
1&
#141750
0&
#141875
1$
1&
#142000
0&
#142125
b1011 )
0$
1&
#142250
0&
#142375
1$
1&
#142500
0&
#142625
b1010 )
0$
1&
#142750
0&
#142875
1$
1&
#143000
0&
#143125
b1001 )
0$
1&
#143250
0&
#143375
1$
1&
#143500
0&
#143625
b1000 )
0$
1&
#143750
0&
#143875
1$
1&
#144000
0&
#144125
b111 )
0$
1&
#144250
0&
#144375
1$
1&
#144500
0&
#144625
b110 )
0$
1&
#144750
0&
#144875
1$
1&
#145000
0&
#145125
b101 )
0$
1&
#145250
0&
#145375
1$
1&
#145500
0&
#145625
b100 )
0$
1&
#145750
0&
#145875
1$
1&
#146000
0&
#146125
b11 )
0$
1&
#146250
0&
#146375
1$
1&
#146500
0&
#146625
b10 )
0$
1&
#146750
0&
#146875
1$
1&
#147000
0&
#147125
b1 )
0$
1&
#147250
0&
#147375
1$
1&
#147500
0&
#147625
1#
b0 )
0$
1&
#147750
0&
#147875
1*
1$
1&
#148000
0&
#148125
b1 +
b11111 )
0#
0$
1"
1&
#148250
0&
#148375
0*
1&
#148500
0&
#148625
1#
0"
1&
#148750
0&
#148875
1$
1&
#149000
0&
#149125
b11110 )
0$
1&
#149250
0&
#149375
1$
1&
#149500
0&
#149625
b11101 )
0$
1&
#149750
0&
#149875
1$
1&
#150000
0&
#150125
b11100 )
0$
1&
#150250
0&
#150375
1$
1&
#150500
0&
#150625
b11011 )
0$
1&
#150750
0&
#150875
1$
1&
#151000
0&
#151125
0#
b11010 )
0$
1&
#151250
0&
#151375
1$
1&
#151500
0&
#151625
b11001 )
0$
1&
#151750
0&
#151875
1$
1&
#152000
0&
#152125
b11000 )
0$
1&
#152250
0&
#152375
1$
1&
#152500
0&
#152625
1#
b10111 )
0$
1&
#152750
0&
#152875
1$
1&
#153000
0&
#153125
0#
b10110 )
0$
1&
#153250
0&
#153375
1$
1&
#153500
0&
#153625
b10101 )
0$
1&
#153750
0&
#153875
1$
1&
#154000
0&
#154125
b10100 )
0$
1&
#154250
0&
#154375
1$
1&
#154500
0&
#154625
b10011 )
0$
1&
#154750
0&
#154875
1$
1&
#155000
0&
#155125
1#
b10010 )
0$
1&
#155250
0&
#155375
1$
1&
#155500
0&
#155625
0#
b10001 )
0$
1&
#155750
0&
#155875
1$
1&
#156000
0&
#156125
b10000 )
0$
1&
#156250
0&
#156375
1$
1&
#156500
0&
#156625
1#
b1111 )
0$
1&
#156750
0&
#156875
1$
1&
