fpga/hdl/fmcw_defines.vh
`define FMCW_DEFAULT_PARAMS parameter \
NTAPS = 120, \
CntW = 7, \
TW = 16, \
IW = 12, \
OW = 16, \
IntW = 29, \
M = 20, \
MW = 5

fpga/hdl/downsample.v
`default_nettype none

`include "fmcw_defines.vh"

module downsample #( `FMCW_DEFAULT_PARAMS )
        (
         input wire          clk_i,
         output reg          clk_o,
         input wire [OW-1:0] data_i,
         output reg [OW-1:0] data_o
         );

        reg [MW-1:0]         cnt;

        initial begin
                cnt = 0;
                clk_o = 0;
        end

        always @(posedge clk_i) begin
                if (cnt == (M>>1)-1) begin
                        cnt <= 0;
                        clk_o <= !clk_o;
                        data_o <= data_i;
                end
                else begin
                        cnt <= cnt + 1;
                        clk_o <= clk_o;
                        data_o <= data_o;
                end
        end

endmodule // downsample

fpga/hdl/tb/downsample_tb.v
`default_nettype none

`include "fmcw_defines.vh"
`include "downsample.v"

`timescale 1ns/1ps
module downsample_tb #( `FMCW_DEFAULT_PARAMS );

        reg clk_i = 0;
        wire clk_o;
        reg [OW-1:0] data_i = 0;
        wire [OW-1:0] data_o;

        initial begin
                $dumpfile("downsample.vcd");
                $dumpvars(0, downsample_tb);

                #10000 $finish;
        end

        always @(posedge clk_i) begin
                data_i <= data_i + 1;
        end

        always #25 clk_i = !clk_i;

        downsample downsample (.clk_i(clk_i),
                               .clk_o(clk_o),
                               .data_i(data_i),
                               .data_o(data_o));

endmodule // downsample_tb

fpga/hdl/tb/downsample.vcd
$date
	Sat Feb  2 14:42:01 2019
$end
$version
	Icarus Verilog
$end
$timescale
	1ps
$end
$scope module downsample_tb $end
$var wire 16 ! data_o [15:0] $end
$var wire 1 " clk_o $end
$var reg 1 # clk_i $end
$var reg 16 $ data_i [15:0] $end
$scope module downsample $end
$var wire 1 # clk_i $end
$var wire 16 % data_i [15:0] $end
$var reg 1 " clk_o $end
$var reg 5 & cnt [4:0] $end
$var reg 16 ' data_o [15:0] $end
$upscope $end
$upscope $end
$enddefinitions $end
#0
$dumpvars
bx '
b0 &
b0 %
b0 $
0#
0"
bx !
$end
#25000
b1 &
b1 $
b1 %
1#
#50000
0#
#75000
b10 $
b10 %
b10 &
1#
#100000
0#
#125000
b11 &
b11 $
b11 %
1#
#150000
0#
#175000
b100 $
b100 %
b100 &
1#
#200000
0#
#225000
b101 &
b101 $
b101 %
1#
#250000
0#
#275000
b110 $
b110 %
b110 &
1#
#300000
0#
#325000
b111 &
b111 $
b111 %
1#
#350000
0#
#375000
b1000 $
b1000 %
b1000 &
1#
#400000
0#
#425000
b1001 &
b1001 $
b1001 %
1#
#450000
0#
#475000
b1010 $
b1010 %
b1001 !
b1001 '
1"
b0 &
1#
#500000
0#
#525000
b1 &
b1011 $
b1011 %
1#
#550000
0#
#575000
b1100 $
b1100 %
b10 &
1#
#600000
0#
#625000
b11 &
b1101 $
b1101 %
1#
#650000
0#
#675000
b1110 $
b1110 %
b100 &
1#
#700000
0#
#725000
b101 &
b1111 $
b1111 %
1#
#750000
0#
#775000
b10000 $
b10000 %
b110 &
1#
#800000
0#
#825000
b111 &
b10001 $
b10001 %
1#
#850000
0#
#875000
b10010 $
b10010 %
b1000 &
1#
#900000
0#
#925000
b1001 &
b10011 $
b10011 %
1#
#950000
0#
#975000
b10100 $
b10100 %
b10011 !
b10011 '
0"
b0 &
1#
#1000000
0#
#1025000
b1 &
b10101 $
b10101 %
1#
#1050000
0#
#1075000
b10110 $
b10110 %
b10 &
1#
#1100000
0#
#1125000
b11 &
b10111 $
b10111 %
1#
#1150000
0#
#1175000
b11000 $
b11000 %
b100 &
1#
#1200000
0#
#1225000
b101 &
b11001 $
b11001 %
1#
#1250000
0#
#1275000
b11010 $
b11010 %
b110 &
1#
#1300000
0#
#1325000
b111 &
b11011 $
b11011 %
1#
#1350000
0#
#1375000
b11100 $
b11100 %
b1000 &
1#
#1400000
0#
#1425000
b1001 &
b11101 $
b11101 %
1#
#1450000
0#
#1475000
b11110 $
b11110 %
b11101 !
b11101 '
1"
b0 &
1#
#1500000
0#
#1525000
b1 &
b11111 $
b11111 %
1#
#1550000
0#
#1575000
b100000 $
b100000 %
b10 &
1#
#1600000
0#
#1625000
b11 &
b100001 $
b100001 %
1#
#1650000
0#
#1675000
b100010 $
b100010 %
b100 &
1#
#1700000
0#
#1725000
b101 &
b100011 $
b100011 %
1#
#1750000
0#
#1775000
b100100 $
b100100 %
b110 &
1#
#1800000
0#
#1825000
b111 &
b100101 $
b100101 %
1#
#1850000
0#
#1875000
b100110 $
b100110 %
b1000 &
1#
#1900000
0#
#1925000
b1001 &
b100111 $
b100111 %
1#
#1950000
0#
#1975000
b101000 $
b101000 %
b100111 !
b100111 '
0"
b0 &
1#
#2000000
0#
#2025000
b1 &
b101001 $
b101001 %
1#
#2050000
0#
#2075000
b101010 $
b101010 %
b10 &
1#
#2100000
0#
#2125000
b11 &
b101011 $
b101011 %
1#
#2150000
0#
#2175000
b101100 $
b101100 %
b100 &
1#
#2200000
0#
#2225000
b101 &
b101101 $
b101101 %
1#
#2250000
0#
#2275000
b101110 $
b101110 %
b110 &
1#
#2300000
0#
#2325000
b111 &
b101111 $
b101111 %
1#
#2350000
0#
#2375000
b110000 $
b110000 %
b1000 &
1#
#2400000
0#
#2425000
b1001 &
b110001 $
b110001 %
1#
#2450000
0#
#2475000
b110010 $
b110010 %
b110001 !
b110001 '
1"
b0 &
1#
#2500000
0#
#2525000
b1 &
b110011 $
b110011 %
1#
#2550000
0#
#2575000
b110100 $
b110100 %
b10 &
1#
#2600000
0#
#2625000
b11 &
b110101 $
b110101 %
1#
#2650000
0#
#2675000
b110110 $
b110110 %
b100 &
1#
#2700000
0#
#2725000
b101 &
b110111 $
b110111 %
1#
#2750000
0#
#2775000
b111000 $
b111000 %
b110 &
1#
#2800000
0#
#2825000
b111 &
b111001 $
b111001 %
1#
#2850000
0#
#2875000
b111010 $
b111010 %
b1000 &
1#
#2900000
0#
#2925000
b1001 &
b111011 $
b111011 %
1#
#2950000
0#
#2975000
b111100 $
b111100 %
b111011 !
b111011 '
0"
b0 &
1#
#3000000
0#
#3025000
b1 &
b111101 $
b111101 %
1#
#3050000
0#
#3075000
b111110 $
b111110 %
b10 &
1#
#3100000
0#
#3125000
b11 &
b111111 $
b111111 %
1#
#3150000
0#
#3175000
b1000000 $
b1000000 %
b100 &
1#
#3200000
0#
#3225000
b101 &
b1000001 $
b1000001 %
1#
#3250000
0#
#3275000
b1000010 $
b1000010 %
b110 &
1#
#3300000
0#
#3325000
b111 &
b1000011 $
b1000011 %
1#
#3350000
0#
#3375000
b1000100 $
b1000100 %
b1000 &
1#
#3400000
0#
#3425000
b1001 &
b1000101 $
b1000101 %
1#
#3450000
0#
#3475000
b1000110 $
b1000110 %
b1000101 !
b1000101 '
1"
b0 &
1#
#3500000
0#
#3525000
b1 &
b1000111 $
b1000111 %
1#
#3550000
0#
#3575000
b1001000 $
b1001000 %
b10 &
1#
#3600000
0#
#3625000
b11 &
b1001001 $
b1001001 %
1#
#3650000
0#
#3675000
b1001010 $
b1001010 %
b100 &
1#
#3700000
0#
#3725000
b101 &
b1001011 $
b1001011 %
1#
#3750000
0#
#3775000
b1001100 $
b1001100 %
b110 &
1#
#3800000
0#
#3825000
b111 &
b1001101 $
b1001101 %
1#
#3850000
0#
#3875000
b1001110 $
b1001110 %
b1000 &
1#
#3900000
0#
#3925000
b1001 &
b1001111 $
b1001111 %
1#
#3950000
0#
#3975000
b1010000 $
b1010000 %
b1001111 !
b1001111 '
0"
b0 &
1#
#4000000
0#
#4025000
b1 &
b1010001 $
b1010001 %
1#
#4050000
0#
#4075000
b1010010 $
b1010010 %
b10 &
1#
#4100000
0#
#4125000
b11 &
b1010011 $
b1010011 %
1#
#4150000
0#
#4175000
b1010100 $
b1010100 %
b100 &
1#
#4200000
0#
#4225000
b101 &
b1010101 $
b1010101 %
1#
#4250000
0#
#4275000
b1010110 $
b1010110 %
b110 &
1#
#4300000
0#
#4325000
b111 &
b1010111 $
b1010111 %
1#
#4350000
0#
#4375000
b1011000 $
b1011000 %
b1000 &
1#
#4400000
0#
#4425000
b1001 &
b1011001 $
b1011001 %
1#
#4450000
0#
#4475000
b1011010 $
b1011010 %
b1011001 !
b1011001 '
1"
b0 &
1#
#4500000
0#
#4525000
b1 &
b1011011 $
b1011011 %
1#
#4550000
0#
#4575000
b1011100 $
b1011100 %
b10 &
1#
#4600000
0#
#4625000
b11 &
b1011101 $
b1011101 %
1#
#4650000
0#
#4675000
b1011110 $
b1011110 %
b100 &
1#
#4700000
0#
#4725000
b101 &
b1011111 $
b1011111 %
1#
#4750000
0#
#4775000
b1100000 $
b1100000 %
b110 &
1#
#4800000
0#
#4825000
b111 &
b1100001 $
b1100001 %
1#
#4850000
0#
#4875000
b1100010 $
b1100010 %
b1000 &
1#
#4900000
0#
#4925000
b1001 &
b1100011 $
b1100011 %
1#
#4950000
0#
#4975000
b1100100 $
b1100100 %
b1100011 !
b1100011 '
0"
b0 &
1#
#5000000
0#
#5025000
b1 &
b1100101 $
b1100101 %
1#
#5050000
0#
#5075000
b1100110 $
b1100110 %
b10 &
1#
#5100000
0#
#5125000
b11 &
b1100111 $
b1100111 %
1#
#5150000
0#
#5175000
b1101000 $
b1101000 %
b100 &
1#
#5200000
0#
#5225000
b101 &
b1101001 $
b1101001 %
1#
#5250000
0#
#5275000
b1101010 $
b1101010 %
b110 &
1#
#5300000
0#
#5325000
b111 &
b1101011 $
b1101011 %
1#
#5350000
0#
#5375000
b1101100 $
b1101100 %
b1000 &
1#
#5400000
0#
#5425000
b1001 &
b1101101 $
b1101101 %
1#
#5450000
0#
#5475000
b1101110 $
b1101110 %
b1101101 !
b1101101 '
1"
b0 &
1#
#5500000
0#
#5525000
b1 &
b1101111 $
b1101111 %
1#
#5550000
0#
#5575000
b1110000 $
b1110000 %
b10 &
1#
#5600000
0#
#5625000
b11 &
b1110001 $
b1110001 %
1#
#5650000
0#
#5675000
b1110010 $
b1110010 %
b100 &
1#
#5700000
0#
#5725000
b101 &
b1110011 $
b1110011 %
1#
#5750000
0#
#5775000
b1110100 $
b1110100 %
b110 &
1#
#5800000
0#
#5825000
b111 &
b1110101 $
b1110101 %
1#
#5850000
0#
#5875000
b1110110 $
b1110110 %
b1000 &
1#
#5900000
0#
#5925000
b1001 &
b1110111 $
b1110111 %
1#
#5950000
0#
#5975000
b1111000 $
b1111000 %
b1110111 !
b1110111 '
0"
b0 &
1#
#6000000
0#
#6025000
b1 &
b1111001 $
b1111001 %
1#
#6050000
0#
#6075000
b1111010 $
b1111010 %
b10 &
1#
#6100000
0#
#6125000
b11 &
b1111011 $
b1111011 %
1#
#6150000
0#
#6175000
b1111100 $
b1111100 %
b100 &
1#
#6200000
0#
#6225000
b101 &
b1111101 $
b1111101 %
1#
#6250000
0#
#6275000
b1111110 $
b1111110 %
b110 &
1#
#6300000
0#
#6325000
b111 &
b1111111 $
b1111111 %
1#
#6350000
0#
#6375000
b10000000 $
b10000000 %
b1000 &
1#
#6400000
0#
#6425000
b1001 &
b10000001 $
b10000001 %
1#
#6450000
0#
#6475000
b10000010 $
b10000010 %
b10000001 !
b10000001 '
1"
b0 &
1#
#6500000
0#
#6525000
b1 &
b10000011 $
b10000011 %
1#
#6550000
0#
#6575000
b10000100 $
b10000100 %
b10 &
1#
#6600000
0#
#6625000
b11 &
b10000101 $
b10000101 %
1#
#6650000
0#
#6675000
b10000110 $
b10000110 %
b100 &
1#
#6700000
0#
#6725000
b101 &
b10000111 $
b10000111 %
1#
#6750000
0#
#6775000
b10001000 $
b10001000 %
b110 &
1#
#6800000
0#
#6825000
b111 &
b10001001 $
b10001001 %
1#
#6850000
0#
#6875000
b10001010 $
b10001010 %
b1000 &
1#
#6900000
0#
#6925000
b1001 &
b10001011 $
b10001011 %
1#
#6950000
0#
#6975000
b10001100 $
b10001100 %
b10001011 !
b10001011 '
0"
b0 &
1#
#7000000
0#
#7025000
b1 &
b10001101 $
b10001101 %
1#
#7050000
0#
#7075000
b10001110 $
b10001110 %
b10 &
1#
#7100000
0#
#7125000
b11 &
b10001111 $
b10001111 %
1#
#7150000
0#
#7175000
b10010000 $
b10010000 %
b100 &
1#
#7200000
0#
#7225000
b101 &
b10010001 $
b10010001 %
1#
#7250000
0#
#7275000
b10010010 $
b10010010 %
b110 &
1#
#7300000
0#
#7325000
b111 &
b10010011 $
b10010011 %
1#
#7350000
0#
#7375000
b10010100 $
b10010100 %
b1000 &
1#
#7400000
0#
#7425000
b1001 &
b10010101 $
b10010101 %
1#
#7450000
0#
#7475000
b10010110 $
b10010110 %
b10010101 !
b10010101 '
1"
b0 &
1#
#7500000
0#
#7525000
b1 &
b10010111 $
b10010111 %
1#
#7550000
0#
#7575000
b10011000 $
b10011000 %
b10 &
1#
#7600000
0#
#7625000
b11 &
b10011001 $
b10011001 %
1#
#7650000
0#
#7675000
b10011010 $
b10011010 %
b100 &
1#
#7700000
0#
#7725000
b101 &
b10011011 $
b10011011 %
1#
#7750000
0#
#7775000
b10011100 $
b10011100 %
b110 &
1#
#7800000
0#
#7825000
b111 &
b10011101 $
b10011101 %
1#
#7850000
0#
#7875000
b10011110 $
b10011110 %
b1000 &
1#
#7900000
0#
#7925000
b1001 &
b10011111 $
b10011111 %
1#
#7950000
0#
#7975000
b10100000 $
b10100000 %
b10011111 !
b10011111 '
0"
b0 &
1#
#8000000
0#
#8025000
b1 &
b10100001 $
b10100001 %
1#
#8050000
0#
#8075000
b10100010 $
b10100010 %
b10 &
1#
#8100000
0#
#8125000
b11 &
b10100011 $
b10100011 %
1#
#8150000
0#
#8175000
b10100100 $
b10100100 %
b100 &
1#
#8200000
0#
#8225000
b101 &
b10100101 $
b10100101 %
1#
#8250000
0#
#8275000
b10100110 $
b10100110 %
b110 &
1#
#8300000
0#
#8325000
b111 &
b10100111 $
b10100111 %
1#
#8350000
0#
#8375000
b10101000 $
b10101000 %
b1000 &
1#
#8400000
0#
#8425000
b1001 &
b10101001 $
b10101001 %
1#
#8450000
0#
#8475000
b10101010 $
b10101010 %
b10101001 !
b10101001 '
1"
b0 &
1#
#8500000
0#
#8525000
b1 &
b10101011 $
b10101011 %
1#
#8550000
0#
#8575000
b10101100 $
b10101100 %
b10 &
1#
#8600000
0#
#8625000
b11 &
b10101101 $
b10101101 %
1#
#8650000
0#
#8675000
b10101110 $
b10101110 %
b100 &
1#
#8700000
0#
#8725000
b101 &
b10101111 $
b10101111 %
1#
#8750000
0#
#8775000
b10110000 $
b10110000 %
b110 &
1#
#8800000
0#
#8825000
b111 &
b10110001 $
b10110001 %
1#
#8850000
0#
#8875000
b10110010 $
b10110010 %
b1000 &
1#
#8900000
0#
#8925000
b1001 &
b10110011 $
b10110011 %
1#
#8950000
0#
#8975000
b10110100 $
b10110100 %
b10110011 !
b10110011 '
0"
b0 &
1#
#9000000
0#
#9025000
b1 &
b10110101 $
b10110101 %
1#
#9050000
0#
#9075000
b10110110 $
b10110110 %
b10 &
1#
#9100000
0#
#9125000
b11 &
b10110111 $
b10110111 %
1#
#9150000
0#
#9175000
b10111000 $
b10111000 %
b100 &
1#
#9200000
0#
#9225000
b101 &
b10111001 $
b10111001 %
1#
#9250000
0#
#9275000
b10111010 $
b10111010 %
b110 &
1#
#9300000
0#
#9325000
b111 &
b10111011 $
b10111011 %
1#
#9350000
0#
#9375000
b10111100 $
b10111100 %
b1000 &
1#
#9400000
0#
#9425000
b1001 &
b10111101 $
b10111101 %
1#
#9450000
0#
#9475000
b10111110 $
b10111110 %
b10111101 !
b10111101 '
1"
b0 &
1#
#9500000
0#
#9525000
b1 &
b10111111 $
b10111111 %
1#
#9550000
0#
#9575000
b11000000 $
b11000000 %
b10 &
1#
#9600000
0#
#9625000
b11 &
b11000001 $
b11000001 %
1#
#9650000
0#
#9675000
b11000010 $
b11000010 %
b100 &
1#
#9700000
0#
#9725000
b101 &
b11000011 $
b11000011 %
1#
#9750000
0#
#9775000
b11000100 $
b11000100 %
b110 &
1#
#9800000
0#
#9825000
b111 &
b11000101 $
b11000101 %
1#
#9850000
0#
#9875000
b11000110 $
b11000110 %
b1000 &
1#
#9900000
0#
#9925000
b1001 &
b11000111 $
b11000111 %
1#
#9950000
0#
#9975000
b11001000 $
b11001000 %
b11000111 !
b11000111 '
0"
b0 &
1#
