fpga/hdl/fmcw_defines.vh
`define FMCW_DEFAULT_PARAMS parameter \
NTAPS = 120, \
CntW = 7, \
TW = 16, \
IW = 12, \
OW = 24, \
IntW = 29, \
USBDW = 8, \
SDDW = 4, \
GPIOW = 6, \
FFT_N = 1024, \
FFT_STAGES = 5, \
FFT_NLOG2 = 10, \
FFTDW = 32, \
TWIDDLE_WIDTH = 10, \
Cnt_STAGE = 3, \
M = 20, \
MW = 5

fpga/hdl/downsample.v
`default_nettype none

`include "fmcw_defines.vh"

module downsample #( `FMCW_DEFAULT_PARAMS )
        (
         input wire          clk_i,
         output reg          clk_o,
         input wire [OW-1:0] data_i,
         output reg [OW-1:0] data_o
         );

        reg [MW-1:0]         cnt;

        initial begin
                cnt = 0;
                clk_o = 0;
        end

        always @(posedge clk_i) begin
                if (cnt == (M>>1)-1) begin /* M is the downsampling rate */
                        cnt <= 0;
                        clk_o <= !clk_o;
                        data_o <= data_i;
                end
                else begin
                        cnt <= cnt + 1;
                        clk_o <= clk_o;
                        data_o <= data_o;
                end
        end

endmodule // downsample

fpga/hdl/tb/downsample_tb.v
`default_nettype none

`include "fmcw_defines.vh"
`include "downsample.v"

`timescale 1ns/1ps
module downsample_tb #( `FMCW_DEFAULT_PARAMS );

        reg clk_i = 0;
        wire clk_o;
        reg [OW-1:0] data_i = 0;
        wire [OW-1:0] data_o;

        initial begin
                $dumpfile("downsample.vcd");
                $dumpvars(0, downsample_tb);

                #10000 $finish;
        end

        always @(posedge clk_i) begin
                data_i <= data_i + 1;
        end

        always #12.5 clk_i = !clk_i;

        downsample downsample (.clk_i(clk_i),
                               .clk_o(clk_o),
                               .data_i(data_i),
                               .data_o(data_o));

endmodule // downsample_tb

fpga/hdl/tb/downsample.vcd
$date
	Fri Jul 26 17:34:10 2019
$end
$version
	Icarus Verilog
$end
$timescale
	1ps
$end
$scope module downsample_tb $end
$var wire 16 ! data_o [15:0] $end
$var wire 1 " clk_o $end
$var reg 1 # clk_i $end
$var reg 16 $ data_i [15:0] $end
$scope module downsample $end
$var wire 1 # clk_i $end
$var wire 16 % data_i [15:0] $end
$var reg 1 " clk_o $end
$var reg 5 & cnt [4:0] $end
$var reg 16 ' data_o [15:0] $end
$upscope $end
$upscope $end
$enddefinitions $end
#0
$dumpvars
bx '
b0 &
b0 %
b0 $
0#
0"
bx !
$end
#12500
b1 &
b1 $
b1 %
1#
#25000
0#
#37500
b10 $
b10 %
b10 &
1#
#50000
0#
#62500
b11 &
b11 $
b11 %
1#
#75000
0#
#87500
b100 $
b100 %
b100 &
1#
#100000
0#
#112500
b101 &
b101 $
b101 %
1#
#125000
0#
#137500
b110 $
b110 %
b110 &
1#
#150000
0#
#162500
b111 &
b111 $
b111 %
1#
#175000
0#
#187500
b1000 $
b1000 %
b1000 &
1#
#200000
0#
#212500
b1001 &
b1001 $
b1001 %
1#
#225000
0#
#237500
b1010 $
b1010 %
b1001 !
b1001 '
1"
b0 &
1#
#250000
0#
#262500
b1 &
b1011 $
b1011 %
1#
#275000
0#
#287500
b1100 $
b1100 %
b10 &
1#
#300000
0#
#312500
b11 &
b1101 $
b1101 %
1#
#325000
0#
#337500
b1110 $
b1110 %
b100 &
1#
#350000
0#
#362500
b101 &
b1111 $
b1111 %
1#
#375000
0#
#387500
b10000 $
b10000 %
b110 &
1#
#400000
0#
#412500
b111 &
b10001 $
b10001 %
1#
#425000
0#
#437500
b10010 $
b10010 %
b1000 &
1#
#450000
0#
#462500
b1001 &
b10011 $
b10011 %
1#
#475000
0#
#487500
b10100 $
b10100 %
b10011 !
b10011 '
0"
b0 &
1#
#500000
0#
#512500
b1 &
b10101 $
b10101 %
1#
#525000
0#
#537500
b10110 $
b10110 %
b10 &
1#
#550000
0#
#562500
b11 &
b10111 $
b10111 %
1#
#575000
0#
#587500
b11000 $
b11000 %
b100 &
1#
#600000
0#
#612500
b101 &
b11001 $
b11001 %
1#
#625000
0#
#637500
b11010 $
b11010 %
b110 &
1#
#650000
0#
#662500
b111 &
b11011 $
b11011 %
1#
#675000
0#
#687500
b11100 $
b11100 %
b1000 &
1#
#700000
0#
#712500
b1001 &
b11101 $
b11101 %
1#
#725000
0#
#737500
b11110 $
b11110 %
b11101 !
b11101 '
1"
b0 &
1#
#750000
0#
#762500
b1 &
b11111 $
b11111 %
1#
#775000
0#
#787500
b100000 $
b100000 %
b10 &
1#
#800000
0#
#812500
b11 &
b100001 $
b100001 %
1#
#825000
0#
#837500
b100010 $
b100010 %
b100 &
1#
#850000
0#
#862500
b101 &
b100011 $
b100011 %
1#
#875000
0#
#887500
b100100 $
b100100 %
b110 &
1#
#900000
0#
#912500
b111 &
b100101 $
b100101 %
1#
#925000
0#
#937500
b100110 $
b100110 %
b1000 &
1#
#950000
0#
#962500
b1001 &
b100111 $
b100111 %
1#
#975000
0#
#987500
b101000 $
b101000 %
b100111 !
b100111 '
0"
b0 &
1#
#1000000
0#
#1012500
b1 &
b101001 $
b101001 %
1#
#1025000
0#
#1037500
b101010 $
b101010 %
b10 &
1#
#1050000
0#
#1062500
b11 &
b101011 $
b101011 %
1#
#1075000
0#
#1087500
b101100 $
b101100 %
b100 &
1#
#1100000
0#
#1112500
b101 &
b101101 $
b101101 %
1#
#1125000
0#
#1137500
b101110 $
b101110 %
b110 &
1#
#1150000
0#
#1162500
b111 &
b101111 $
b101111 %
1#
#1175000
0#
#1187500
b110000 $
b110000 %
b1000 &
1#
#1200000
0#
#1212500
b1001 &
b110001 $
b110001 %
1#
#1225000
0#
#1237500
b110010 $
b110010 %
b110001 !
b110001 '
1"
b0 &
1#
#1250000
0#
#1262500
b1 &
b110011 $
b110011 %
1#
#1275000
0#
#1287500
b110100 $
b110100 %
b10 &
1#
#1300000
0#
#1312500
b11 &
b110101 $
b110101 %
1#
#1325000
0#
#1337500
b110110 $
b110110 %
b100 &
1#
#1350000
0#
#1362500
b101 &
b110111 $
b110111 %
1#
#1375000
0#
#1387500
b111000 $
b111000 %
b110 &
1#
#1400000
0#
#1412500
b111 &
b111001 $
b111001 %
1#
#1425000
0#
#1437500
b111010 $
b111010 %
b1000 &
1#
#1450000
0#
#1462500
b1001 &
b111011 $
b111011 %
1#
#1475000
0#
#1487500
b111100 $
b111100 %
b111011 !
b111011 '
0"
b0 &
1#
#1500000
0#
#1512500
b1 &
b111101 $
b111101 %
1#
#1525000
0#
#1537500
b111110 $
b111110 %
b10 &
1#
#1550000
0#
#1562500
b11 &
b111111 $
b111111 %
1#
#1575000
0#
#1587500
b1000000 $
b1000000 %
b100 &
1#
#1600000
0#
#1612500
b101 &
b1000001 $
b1000001 %
1#
#1625000
0#
#1637500
b1000010 $
b1000010 %
b110 &
1#
#1650000
0#
#1662500
b111 &
b1000011 $
b1000011 %
1#
#1675000
0#
#1687500
b1000100 $
b1000100 %
b1000 &
1#
#1700000
0#
#1712500
b1001 &
b1000101 $
b1000101 %
1#
#1725000
0#
#1737500
b1000110 $
b1000110 %
b1000101 !
b1000101 '
1"
b0 &
1#
#1750000
0#
#1762500
b1 &
b1000111 $
b1000111 %
1#
#1775000
0#
#1787500
b1001000 $
b1001000 %
b10 &
1#
#1800000
0#
#1812500
b11 &
b1001001 $
b1001001 %
1#
#1825000
0#
#1837500
b1001010 $
b1001010 %
b100 &
1#
#1850000
0#
#1862500
b101 &
b1001011 $
b1001011 %
1#
#1875000
0#
#1887500
b1001100 $
b1001100 %
b110 &
1#
#1900000
0#
#1912500
b111 &
b1001101 $
b1001101 %
1#
#1925000
0#
#1937500
b1001110 $
b1001110 %
b1000 &
1#
#1950000
0#
#1962500
b1001 &
b1001111 $
b1001111 %
1#
#1975000
0#
#1987500
b1010000 $
b1010000 %
b1001111 !
b1001111 '
0"
b0 &
1#
#2000000
0#
#2012500
b1 &
b1010001 $
b1010001 %
1#
#2025000
0#
#2037500
b1010010 $
b1010010 %
b10 &
1#
#2050000
0#
#2062500
b11 &
b1010011 $
b1010011 %
1#
#2075000
0#
#2087500
b1010100 $
b1010100 %
b100 &
1#
#2100000
0#
#2112500
b101 &
b1010101 $
b1010101 %
1#
#2125000
0#
#2137500
b1010110 $
b1010110 %
b110 &
1#
#2150000
0#
#2162500
b111 &
b1010111 $
b1010111 %
1#
#2175000
0#
#2187500
b1011000 $
b1011000 %
b1000 &
1#
#2200000
0#
#2212500
b1001 &
b1011001 $
b1011001 %
1#
#2225000
0#
#2237500
b1011010 $
b1011010 %
b1011001 !
b1011001 '
1"
b0 &
1#
#2250000
0#
#2262500
b1 &
b1011011 $
b1011011 %
1#
#2275000
0#
#2287500
b1011100 $
b1011100 %
b10 &
1#
#2300000
0#
#2312500
b11 &
b1011101 $
b1011101 %
1#
#2325000
0#
#2337500
b1011110 $
b1011110 %
b100 &
1#
#2350000
0#
#2362500
b101 &
b1011111 $
b1011111 %
1#
#2375000
0#
#2387500
b1100000 $
b1100000 %
b110 &
1#
#2400000
0#
#2412500
b111 &
b1100001 $
b1100001 %
1#
#2425000
0#
#2437500
b1100010 $
b1100010 %
b1000 &
1#
#2450000
0#
#2462500
b1001 &
b1100011 $
b1100011 %
1#
#2475000
0#
#2487500
b1100100 $
b1100100 %
b1100011 !
b1100011 '
0"
b0 &
1#
#2500000
0#
#2512500
b1 &
b1100101 $
b1100101 %
1#
#2525000
0#
#2537500
b1100110 $
b1100110 %
b10 &
1#
#2550000
0#
#2562500
b11 &
b1100111 $
b1100111 %
1#
#2575000
0#
#2587500
b1101000 $
b1101000 %
b100 &
1#
#2600000
0#
#2612500
b101 &
b1101001 $
b1101001 %
1#
#2625000
0#
#2637500
b1101010 $
b1101010 %
b110 &
1#
#2650000
0#
#2662500
b111 &
b1101011 $
b1101011 %
1#
#2675000
0#
#2687500
b1101100 $
b1101100 %
b1000 &
1#
#2700000
0#
#2712500
b1001 &
b1101101 $
b1101101 %
1#
#2725000
0#
#2737500
b1101110 $
b1101110 %
b1101101 !
b1101101 '
1"
b0 &
1#
#2750000
0#
#2762500
b1 &
b1101111 $
b1101111 %
1#
#2775000
0#
#2787500
b1110000 $
b1110000 %
b10 &
1#
#2800000
0#
#2812500
b11 &
b1110001 $
b1110001 %
1#
#2825000
0#
#2837500
b1110010 $
b1110010 %
b100 &
1#
#2850000
0#
#2862500
b101 &
b1110011 $
b1110011 %
1#
#2875000
0#
#2887500
b1110100 $
b1110100 %
b110 &
1#
#2900000
0#
#2912500
b111 &
b1110101 $
b1110101 %
1#
#2925000
0#
#2937500
b1110110 $
b1110110 %
b1000 &
1#
#2950000
0#
#2962500
b1001 &
b1110111 $
b1110111 %
1#
#2975000
0#
#2987500
b1111000 $
b1111000 %
b1110111 !
b1110111 '
0"
b0 &
1#
#3000000
0#
#3012500
b1 &
b1111001 $
b1111001 %
1#
#3025000
0#
#3037500
b1111010 $
b1111010 %
b10 &
1#
#3050000
0#
#3062500
b11 &
b1111011 $
b1111011 %
1#
#3075000
0#
#3087500
b1111100 $
b1111100 %
b100 &
1#
#3100000
0#
#3112500
b101 &
b1111101 $
b1111101 %
1#
#3125000
0#
#3137500
b1111110 $
b1111110 %
b110 &
1#
#3150000
0#
#3162500
b111 &
b1111111 $
b1111111 %
1#
#3175000
0#
#3187500
b10000000 $
b10000000 %
b1000 &
1#
#3200000
0#
#3212500
b1001 &
b10000001 $
b10000001 %
1#
#3225000
0#
#3237500
b10000010 $
b10000010 %
b10000001 !
b10000001 '
1"
b0 &
1#
#3250000
0#
#3262500
b1 &
b10000011 $
b10000011 %
1#
#3275000
0#
#3287500
b10000100 $
b10000100 %
b10 &
1#
#3300000
0#
#3312500
b11 &
b10000101 $
b10000101 %
1#
#3325000
0#
#3337500
b10000110 $
b10000110 %
b100 &
1#
#3350000
0#
#3362500
b101 &
b10000111 $
b10000111 %
1#
#3375000
0#
#3387500
b10001000 $
b10001000 %
b110 &
1#
#3400000
0#
#3412500
b111 &
b10001001 $
b10001001 %
1#
#3425000
0#
#3437500
b10001010 $
b10001010 %
b1000 &
1#
#3450000
0#
#3462500
b1001 &
b10001011 $
b10001011 %
1#
#3475000
0#
#3487500
b10001100 $
b10001100 %
b10001011 !
b10001011 '
0"
b0 &
1#
#3500000
0#
#3512500
b1 &
b10001101 $
b10001101 %
1#
#3525000
0#
#3537500
b10001110 $
b10001110 %
b10 &
1#
#3550000
0#
#3562500
b11 &
b10001111 $
b10001111 %
1#
#3575000
0#
#3587500
b10010000 $
b10010000 %
b100 &
1#
#3600000
0#
#3612500
b101 &
b10010001 $
b10010001 %
1#
#3625000
0#
#3637500
b10010010 $
b10010010 %
b110 &
1#
#3650000
0#
#3662500
b111 &
b10010011 $
b10010011 %
1#
#3675000
0#
#3687500
b10010100 $
b10010100 %
b1000 &
1#
#3700000
0#
#3712500
b1001 &
b10010101 $
b10010101 %
1#
#3725000
0#
#3737500
b10010110 $
b10010110 %
b10010101 !
b10010101 '
1"
b0 &
1#
#3750000
0#
#3762500
b1 &
b10010111 $
b10010111 %
1#
#3775000
0#
#3787500
b10011000 $
b10011000 %
b10 &
1#
#3800000
0#
#3812500
b11 &
b10011001 $
b10011001 %
1#
#3825000
0#
#3837500
b10011010 $
b10011010 %
b100 &
1#
#3850000
0#
#3862500
b101 &
b10011011 $
b10011011 %
1#
#3875000
0#
#3887500
b10011100 $
b10011100 %
b110 &
1#
#3900000
0#
#3912500
b111 &
b10011101 $
b10011101 %
1#
#3925000
0#
#3937500
b10011110 $
b10011110 %
b1000 &
1#
#3950000
0#
#3962500
b1001 &
b10011111 $
b10011111 %
1#
#3975000
0#
#3987500
b10100000 $
b10100000 %
b10011111 !
b10011111 '
0"
b0 &
1#
#4000000
0#
#4012500
b1 &
b10100001 $
b10100001 %
1#
#4025000
0#
#4037500
b10100010 $
b10100010 %
b10 &
1#
#4050000
0#
#4062500
b11 &
b10100011 $
b10100011 %
1#
#4075000
0#
#4087500
b10100100 $
b10100100 %
b100 &
1#
#4100000
0#
#4112500
b101 &
b10100101 $
b10100101 %
1#
#4125000
0#
#4137500
b10100110 $
b10100110 %
b110 &
1#
#4150000
0#
#4162500
b111 &
b10100111 $
b10100111 %
1#
#4175000
0#
#4187500
b10101000 $
b10101000 %
b1000 &
1#
#4200000
0#
#4212500
b1001 &
b10101001 $
b10101001 %
1#
#4225000
0#
#4237500
b10101010 $
b10101010 %
b10101001 !
b10101001 '
1"
b0 &
1#
#4250000
0#
#4262500
b1 &
b10101011 $
b10101011 %
1#
#4275000
0#
#4287500
b10101100 $
b10101100 %
b10 &
1#
#4300000
0#
#4312500
b11 &
b10101101 $
b10101101 %
1#
#4325000
0#
#4337500
b10101110 $
b10101110 %
b100 &
1#
#4350000
0#
#4362500
b101 &
b10101111 $
b10101111 %
1#
#4375000
0#
#4387500
b10110000 $
b10110000 %
b110 &
1#
#4400000
0#
#4412500
b111 &
b10110001 $
b10110001 %
1#
#4425000
0#
#4437500
b10110010 $
b10110010 %
b1000 &
1#
#4450000
0#
#4462500
b1001 &
b10110011 $
b10110011 %
1#
#4475000
0#
#4487500
b10110100 $
b10110100 %
b10110011 !
b10110011 '
0"
b0 &
1#
#4500000
0#
#4512500
b1 &
b10110101 $
b10110101 %
1#
#4525000
0#
#4537500
b10110110 $
b10110110 %
b10 &
1#
#4550000
0#
#4562500
b11 &
b10110111 $
b10110111 %
1#
#4575000
0#
#4587500
b10111000 $
b10111000 %
b100 &
1#
#4600000
0#
#4612500
b101 &
b10111001 $
b10111001 %
1#
#4625000
0#
#4637500
b10111010 $
b10111010 %
b110 &
1#
#4650000
0#
#4662500
b111 &
b10111011 $
b10111011 %
1#
#4675000
0#
#4687500
b10111100 $
b10111100 %
b1000 &
1#
#4700000
0#
#4712500
b1001 &
b10111101 $
b10111101 %
1#
#4725000
0#
#4737500
b10111110 $
b10111110 %
b10111101 !
b10111101 '
1"
b0 &
1#
#4750000
0#
#4762500
b1 &
b10111111 $
b10111111 %
1#
#4775000
0#
#4787500
b11000000 $
b11000000 %
b10 &
1#
#4800000
0#
#4812500
b11 &
b11000001 $
b11000001 %
1#
#4825000
0#
#4837500
b11000010 $
b11000010 %
b100 &
1#
#4850000
0#
#4862500
b101 &
b11000011 $
b11000011 %
1#
#4875000
0#
#4887500
b11000100 $
b11000100 %
b110 &
1#
#4900000
0#
#4912500
b111 &
b11000101 $
b11000101 %
1#
#4925000
0#
#4937500
b11000110 $
b11000110 %
b1000 &
1#
#4950000
0#
#4962500
b1001 &
b11000111 $
b11000111 %
1#
#4975000
0#
#4987500
b11001000 $
b11001000 %
b11000111 !
b11000111 '
0"
b0 &
1#
#5000000
0#
#5012500
b1 &
b11001001 $
b11001001 %
1#
#5025000
0#
#5037500
b11001010 $
b11001010 %
b10 &
1#
#5050000
0#
#5062500
b11 &
b11001011 $
b11001011 %
1#
#5075000
0#
#5087500
b11001100 $
b11001100 %
b100 &
1#
#5100000
0#
#5112500
b101 &
b11001101 $
b11001101 %
1#
#5125000
0#
#5137500
b11001110 $
b11001110 %
b110 &
1#
#5150000
0#
#5162500
b111 &
b11001111 $
b11001111 %
1#
#5175000
0#
#5187500
b11010000 $
b11010000 %
b1000 &
1#
#5200000
0#
#5212500
b1001 &
b11010001 $
b11010001 %
1#
#5225000
0#
#5237500
b11010010 $
b11010010 %
b11010001 !
b11010001 '
1"
b0 &
1#
#5250000
0#
#5262500
b1 &
b11010011 $
b11010011 %
1#
#5275000
0#
#5287500
b11010100 $
b11010100 %
b10 &
1#
#5300000
0#
#5312500
b11 &
b11010101 $
b11010101 %
1#
#5325000
0#
#5337500
b11010110 $
b11010110 %
b100 &
1#
#5350000
0#
#5362500
b101 &
b11010111 $
b11010111 %
1#
#5375000
0#
#5387500
b11011000 $
b11011000 %
b110 &
1#
#5400000
0#
#5412500
b111 &
b11011001 $
b11011001 %
1#
#5425000
0#
#5437500
b11011010 $
b11011010 %
b1000 &
1#
#5450000
0#
#5462500
b1001 &
b11011011 $
b11011011 %
1#
#5475000
0#
#5487500
b11011100 $
b11011100 %
b11011011 !
b11011011 '
0"
b0 &
1#
#5500000
0#
#5512500
b1 &
b11011101 $
b11011101 %
1#
#5525000
0#
#5537500
b11011110 $
b11011110 %
b10 &
1#
#5550000
0#
#5562500
b11 &
b11011111 $
b11011111 %
1#
#5575000
0#
#5587500
b11100000 $
b11100000 %
b100 &
1#
#5600000
0#
#5612500
b101 &
b11100001 $
b11100001 %
1#
#5625000
0#
#5637500
b11100010 $
b11100010 %
b110 &
1#
#5650000
0#
#5662500
b111 &
b11100011 $
b11100011 %
1#
#5675000
0#
#5687500
b11100100 $
b11100100 %
b1000 &
1#
#5700000
0#
#5712500
b1001 &
b11100101 $
b11100101 %
1#
#5725000
0#
#5737500
b11100110 $
b11100110 %
b11100101 !
b11100101 '
1"
b0 &
1#
#5750000
0#
#5762500
b1 &
b11100111 $
b11100111 %
1#
#5775000
0#
#5787500
b11101000 $
b11101000 %
b10 &
1#
#5800000
0#
#5812500
b11 &
b11101001 $
b11101001 %
1#
#5825000
0#
#5837500
b11101010 $
b11101010 %
b100 &
1#
#5850000
0#
#5862500
b101 &
b11101011 $
b11101011 %
1#
#5875000
0#
#5887500
b11101100 $
b11101100 %
b110 &
1#
#5900000
0#
#5912500
b111 &
b11101101 $
b11101101 %
1#
#5925000
0#
#5937500
b11101110 $
b11101110 %
b1000 &
1#
#5950000
0#
#5962500
b1001 &
b11101111 $
b11101111 %
1#
#5975000
0#
#5987500
b11110000 $
b11110000 %
b11101111 !
b11101111 '
0"
b0 &
1#
#6000000
0#
#6012500
b1 &
b11110001 $
b11110001 %
1#
#6025000
0#
#6037500
b11110010 $
b11110010 %
b10 &
1#
#6050000
0#
#6062500
b11 &
b11110011 $
b11110011 %
1#
#6075000
0#
#6087500
b11110100 $
b11110100 %
b100 &
1#
#6100000
0#
#6112500
b101 &
b11110101 $
b11110101 %
1#
#6125000
0#
#6137500
b11110110 $
b11110110 %
b110 &
1#
#6150000
0#
#6162500
b111 &
b11110111 $
b11110111 %
1#
#6175000
0#
#6187500
b11111000 $
b11111000 %
b1000 &
1#
#6200000
0#
#6212500
b1001 &
b11111001 $
b11111001 %
1#
#6225000
0#
#6237500
b11111010 $
b11111010 %
b11111001 !
b11111001 '
1"
b0 &
1#
#6250000
0#
#6262500
b1 &
b11111011 $
b11111011 %
1#
#6275000
0#
#6287500
b11111100 $
b11111100 %
b10 &
1#
#6300000
0#
#6312500
b11 &
b11111101 $
b11111101 %
1#
#6325000
0#
#6337500
b11111110 $
b11111110 %
b100 &
1#
#6350000
0#
#6362500
b101 &
b11111111 $
b11111111 %
1#
#6375000
0#
#6387500
b100000000 $
b100000000 %
b110 &
1#
#6400000
0#
#6412500
b111 &
b100000001 $
b100000001 %
1#
#6425000
0#
#6437500
b100000010 $
b100000010 %
b1000 &
1#
#6450000
0#
#6462500
b1001 &
b100000011 $
b100000011 %
1#
#6475000
0#
#6487500
b100000100 $
b100000100 %
b100000011 !
b100000011 '
0"
b0 &
1#
#6500000
0#
#6512500
b1 &
b100000101 $
b100000101 %
1#
#6525000
0#
#6537500
b100000110 $
b100000110 %
b10 &
1#
#6550000
0#
#6562500
b11 &
b100000111 $
b100000111 %
1#
#6575000
0#
#6587500
b100001000 $
b100001000 %
b100 &
1#
#6600000
0#
#6612500
b101 &
b100001001 $
b100001001 %
1#
#6625000
0#
#6637500
b100001010 $
b100001010 %
b110 &
1#
#6650000
0#
#6662500
b111 &
b100001011 $
b100001011 %
1#
#6675000
0#
#6687500
b100001100 $
b100001100 %
b1000 &
1#
#6700000
0#
#6712500
b1001 &
b100001101 $
b100001101 %
1#
#6725000
0#
#6737500
b100001110 $
b100001110 %
b100001101 !
b100001101 '
1"
b0 &
1#
#6750000
0#
#6762500
b1 &
b100001111 $
b100001111 %
1#
#6775000
0#
#6787500
b100010000 $
b100010000 %
b10 &
1#
#6800000
0#
#6812500
b11 &
b100010001 $
b100010001 %
1#
#6825000
0#
#6837500
b100010010 $
b100010010 %
b100 &
1#
#6850000
0#
#6862500
b101 &
b100010011 $
b100010011 %
1#
#6875000
0#
#6887500
b100010100 $
b100010100 %
b110 &
1#
#6900000
0#
#6912500
b111 &
b100010101 $
b100010101 %
1#
#6925000
0#
#6937500
b100010110 $
b100010110 %
b1000 &
1#
#6950000
0#
#6962500
b1001 &
b100010111 $
b100010111 %
1#
#6975000
0#
#6987500
b100011000 $
b100011000 %
b100010111 !
b100010111 '
0"
b0 &
1#
#7000000
0#
#7012500
b1 &
b100011001 $
b100011001 %
1#
#7025000
0#
#7037500
b100011010 $
b100011010 %
b10 &
1#
#7050000
0#
#7062500
b11 &
b100011011 $
b100011011 %
1#
#7075000
0#
#7087500
b100011100 $
b100011100 %
b100 &
1#
#7100000
0#
#7112500
b101 &
b100011101 $
b100011101 %
1#
#7125000
0#
#7137500
b100011110 $
b100011110 %
b110 &
1#
#7150000
0#
#7162500
b111 &
b100011111 $
b100011111 %
1#
#7175000
0#
#7187500
b100100000 $
b100100000 %
b1000 &
1#
#7200000
0#
#7212500
b1001 &
b100100001 $
b100100001 %
1#
#7225000
0#
#7237500
b100100010 $
b100100010 %
b100100001 !
b100100001 '
1"
b0 &
1#
#7250000
0#
#7262500
b1 &
b100100011 $
b100100011 %
1#
#7275000
0#
#7287500
b100100100 $
b100100100 %
b10 &
1#
#7300000
0#
#7312500
b11 &
b100100101 $
b100100101 %
1#
#7325000
0#
#7337500
b100100110 $
b100100110 %
b100 &
1#
#7350000
0#
#7362500
b101 &
b100100111 $
b100100111 %
1#
#7375000
0#
#7387500
b100101000 $
b100101000 %
b110 &
1#
#7400000
0#
#7412500
b111 &
b100101001 $
b100101001 %
1#
#7425000
0#
#7437500
b100101010 $
b100101010 %
b1000 &
1#
#7450000
0#
#7462500
b1001 &
b100101011 $
b100101011 %
1#
#7475000
0#
#7487500
b100101100 $
b100101100 %
b100101011 !
b100101011 '
0"
b0 &
1#
#7500000
0#
#7512500
b1 &
b100101101 $
b100101101 %
1#
#7525000
0#
#7537500
b100101110 $
b100101110 %
b10 &
1#
#7550000
0#
#7562500
b11 &
b100101111 $
b100101111 %
1#
#7575000
0#
#7587500
b100110000 $
b100110000 %
b100 &
1#
#7600000
0#
#7612500
b101 &
b100110001 $
b100110001 %
1#
#7625000
0#
#7637500
b100110010 $
b100110010 %
b110 &
1#
#7650000
0#
#7662500
b111 &
b100110011 $
b100110011 %
1#
#7675000
0#
#7687500
b100110100 $
b100110100 %
b1000 &
1#
#7700000
0#
#7712500
b1001 &
b100110101 $
b100110101 %
1#
#7725000
0#
#7737500
b100110110 $
b100110110 %
b100110101 !
b100110101 '
1"
b0 &
1#
#7750000
0#
#7762500
b1 &
b100110111 $
b100110111 %
1#
#7775000
0#
#7787500
b100111000 $
b100111000 %
b10 &
1#
#7800000
0#
#7812500
b11 &
b100111001 $
b100111001 %
1#
#7825000
0#
#7837500
b100111010 $
b100111010 %
b100 &
1#
#7850000
0#
#7862500
b101 &
b100111011 $
b100111011 %
1#
#7875000
0#
#7887500
b100111100 $
b100111100 %
b110 &
1#
#7900000
0#
#7912500
b111 &
b100111101 $
b100111101 %
1#
#7925000
0#
#7937500
b100111110 $
b100111110 %
b1000 &
1#
#7950000
0#
#7962500
b1001 &
b100111111 $
b100111111 %
1#
#7975000
0#
#7987500
b101000000 $
b101000000 %
b100111111 !
b100111111 '
0"
b0 &
1#
#8000000
0#
#8012500
b1 &
b101000001 $
b101000001 %
1#
#8025000
0#
#8037500
b101000010 $
b101000010 %
b10 &
1#
#8050000
0#
#8062500
b11 &
b101000011 $
b101000011 %
1#
#8075000
0#
#8087500
b101000100 $
b101000100 %
b100 &
1#
#8100000
0#
#8112500
b101 &
b101000101 $
b101000101 %
1#
#8125000
0#
#8137500
b101000110 $
b101000110 %
b110 &
1#
#8150000
0#
#8162500
b111 &
b101000111 $
b101000111 %
1#
#8175000
0#
#8187500
b101001000 $
b101001000 %
b1000 &
1#
#8200000
0#
#8212500
b1001 &
b101001001 $
b101001001 %
1#
#8225000
0#
#8237500
b101001010 $
b101001010 %
b101001001 !
b101001001 '
1"
b0 &
1#
#8250000
0#
#8262500
b1 &
b101001011 $
b101001011 %
1#
#8275000
0#
#8287500
b101001100 $
b101001100 %
b10 &
1#
#8300000
0#
#8312500
b11 &
b101001101 $
b101001101 %
1#
#8325000
0#
#8337500
b101001110 $
b101001110 %
b100 &
1#
#8350000
0#
#8362500
b101 &
b101001111 $
b101001111 %
1#
#8375000
0#
#8387500
b101010000 $
b101010000 %
b110 &
1#
#8400000
0#
#8412500
b111 &
b101010001 $
b101010001 %
1#
#8425000
0#
#8437500
b101010010 $
b101010010 %
b1000 &
1#
#8450000
0#
#8462500
b1001 &
b101010011 $
b101010011 %
1#
#8475000
0#
#8487500
b101010100 $
b101010100 %
b101010011 !
b101010011 '
0"
b0 &
1#
#8500000
0#
#8512500
b1 &
b101010101 $
b101010101 %
1#
#8525000
0#
#8537500
b101010110 $
b101010110 %
b10 &
1#
#8550000
0#
#8562500
b11 &
b101010111 $
b101010111 %
1#
#8575000
0#
#8587500
b101011000 $
b101011000 %
b100 &
1#
#8600000
0#
#8612500
b101 &
b101011001 $
b101011001 %
1#
#8625000
0#
#8637500
b101011010 $
b101011010 %
b110 &
1#
#8650000
0#
#8662500
b111 &
b101011011 $
b101011011 %
1#
#8675000
0#
#8687500
b101011100 $
b101011100 %
b1000 &
1#
#8700000
0#
#8712500
b1001 &
b101011101 $
b101011101 %
1#
#8725000
0#
#8737500
b101011110 $
b101011110 %
b101011101 !
b101011101 '
1"
b0 &
1#
#8750000
0#
#8762500
b1 &
b101011111 $
b101011111 %
1#
#8775000
0#
#8787500
b101100000 $
b101100000 %
b10 &
1#
#8800000
0#
#8812500
b11 &
b101100001 $
b101100001 %
1#
#8825000
0#
#8837500
b101100010 $
b101100010 %
b100 &
1#
#8850000
0#
#8862500
b101 &
b101100011 $
b101100011 %
1#
#8875000
0#
#8887500
b101100100 $
b101100100 %
b110 &
1#
#8900000
0#
#8912500
b111 &
b101100101 $
b101100101 %
1#
#8925000
0#
#8937500
b101100110 $
b101100110 %
b1000 &
1#
#8950000
0#
#8962500
b1001 &
b101100111 $
b101100111 %
1#
#8975000
0#
#8987500
b101101000 $
b101101000 %
b101100111 !
b101100111 '
0"
b0 &
1#
#9000000
0#
#9012500
b1 &
b101101001 $
b101101001 %
1#
#9025000
0#
#9037500
b101101010 $
b101101010 %
b10 &
1#
#9050000
0#
#9062500
b11 &
b101101011 $
b101101011 %
1#
#9075000
0#
#9087500
b101101100 $
b101101100 %
b100 &
1#
#9100000
0#
#9112500
b101 &
b101101101 $
b101101101 %
1#
#9125000
0#
#9137500
b101101110 $
b101101110 %
b110 &
1#
#9150000
0#
#9162500
b111 &
b101101111 $
b101101111 %
1#
#9175000
0#
#9187500
b101110000 $
b101110000 %
b1000 &
1#
#9200000
0#
#9212500
b1001 &
b101110001 $
b101110001 %
1#
#9225000
0#
#9237500
b101110010 $
b101110010 %
b101110001 !
b101110001 '
1"
b0 &
1#
#9250000
0#
#9262500
b1 &
b101110011 $
b101110011 %
1#
#9275000
0#
#9287500
b101110100 $
b101110100 %
b10 &
1#
#9300000
0#
#9312500
b11 &
b101110101 $
b101110101 %
1#
#9325000
0#
#9337500
b101110110 $
b101110110 %
b100 &
1#
#9350000
0#
#9362500
b101 &
b101110111 $
b101110111 %
1#
#9375000
0#
#9387500
b101111000 $
b101111000 %
b110 &
1#
#9400000
0#
#9412500
b111 &
b101111001 $
b101111001 %
1#
#9425000
0#
#9437500
b101111010 $
b101111010 %
b1000 &
1#
#9450000
0#
#9462500
b1001 &
b101111011 $
b101111011 %
1#
#9475000
0#
#9487500
b101111100 $
b101111100 %
b101111011 !
b101111011 '
0"
b0 &
1#
#9500000
0#
