fpga/hdl/fmcw_defines.vh
`define FMCW_DEFAULT_PARAMS parameter \
NTAPS = 120, \
CntW = 7, \
TW = 16, \
IW = 12, \
OW = 16, \
IntW = 29, \
M = 20, \
MW = 5

fpga/hdl/fir.v
`default_nettype none

`include "fmcw_defines.vh"

module fir #( `FMCW_DEFAULT_PARAMS )
        (
         input wire           clk,
         input wire           rst,
         input wire           ce,
         input wire [IW-1:0]  data_i,
         output wire [OW-1:0] data_o
         );

        reg [TW-1:0]          h [0:NTAPS-1];
        reg [IntW-1:0]        y [0:NTAPS-1];
        reg [CntW-1:0]        i;

        initial begin
                $readmemh("taps.hex", h);
                for (i=0; i<NTAPS; i=i+1) begin
                        y[i] = 0;
                end
                i = 0;
        end

        always @(posedge clk, negedge rst) begin
                if (!rst) begin
                        for (i=0; i<NTAPS; i=i+1) begin
                                y[i] <= 0;
                        end
                end else if (ce) begin
                        y[0] <= data_i * h[NTAPS-1];
                        for (i=1; i<NTAPS; i=i+1) begin
                                y[i] <= y[i-1] + (data_i * h[NTAPS-1-i]);
                        end
                end else begin
                        for (i=0; i<NTAPS-1; i=i+1) begin
                                y[i] <= y[i];
                        end
                end
        end

        assign data_o = (y[NTAPS-1]>>OW);

endmodule // fir

fpga/hdl/tb/fir_tb.v
`default_nettype none

`include "../fmcw_defines.vh"
`include "../fir.v"

`timescale 1ns/1ps
module fir_tb #( `FMCW_DEFAULT_PARAMS );

        reg clk = 0;
        reg [IW-1:0] data_i = 1<<11;
        // reg [IW-1:0] data_i = {{IW-1{1'b0}},1'b1};
        wire [OW-1:0] data_o;

        initial begin
                $dumpfile("fir.vcd");
                $dumpvars(0, fir_tb);

                #50 data_i = 0;

                #10000 $finish;
        end

        always #25 clk = !clk;

        fir fir (.clk(clk),
                 .rst(1'b1),
                 .ce(1'b1),
                 .data_i(data_i),
                 .data_o(data_o));

endmodule // fir_tb

fpga/hdl/tb/fir.vcd
$date
	Sat Feb  2 14:01:56 2019
$end
$version
	Icarus Verilog
$end
$timescale
	1ps
$end
$scope module fir_tb $end
$var wire 16 ! data_o [15:0] $end
$var reg 1 " clk $end
$var reg 12 # data_i [11:0] $end
$scope module fir $end
$var wire 1 $ ce $end
$var wire 1 " clk $end
$var wire 12 % data_i [11:0] $end
$var wire 1 & rst $end
$var wire 16 ' data_o [15:0] $end
$var reg 7 ( i [6:0] $end
$upscope $end
$upscope $end
$enddefinitions $end
#0
$dumpvars
b0 (
b0 '
1&
b100000000000 %
1$
b100000000000 #
0"
b0 !
$end
#25000
b1001 !
b1001 '
b1111000 (
1"
#50000
0"
b0 #
b0 %
#75000
b100 !
b100 '
b1111000 (
1"
#100000
0"
#125000
b101 !
b101 '
b1111000 (
1"
#150000
0"
#175000
b110 !
b110 '
b1111000 (
1"
#200000
0"
#225000
b111 !
b111 '
b1111000 (
1"
#250000
0"
#275000
b1111000 (
1"
#300000
0"
#325000
b1111000 (
1"
#350000
0"
#375000
b1111000 (
1"
#400000
0"
#425000
b110 !
b110 '
b1111000 (
1"
#450000
0"
#475000
b100 !
b100 '
b1111000 (
1"
#500000
0"
#525000
b10 !
b10 '
b1111000 (
1"
#550000
0"
#575000
b0 !
b0 '
b1111000 (
1"
#600000
0"
#625000
b11111111101 !
b11111111101 '
b1111000 (
1"
#650000
0"
#675000
b11111111011 !
b11111111011 '
b1111000 (
1"
#700000
0"
#725000
b11111111000 !
b11111111000 '
b1111000 (
1"
#750000
0"
#775000
b11111110110 !
b11111110110 '
b1111000 (
1"
#800000
0"
#825000
b11111110100 !
b11111110100 '
b1111000 (
1"
#850000
0"
#875000
b11111110010 !
b11111110010 '
b1111000 (
1"
#900000
0"
#925000
b11111110001 !
b11111110001 '
b1111000 (
1"
#950000
0"
#975000
b1111000 (
1"
#1000000
0"
#1025000
b11111110010 !
b11111110010 '
b1111000 (
1"
#1050000
0"
#1075000
b11111110011 !
b11111110011 '
b1111000 (
1"
#1100000
0"
#1125000
b11111110110 !
b11111110110 '
b1111000 (
1"
#1150000
0"
#1175000
b11111111001 !
b11111111001 '
b1111000 (
1"
#1200000
0"
#1225000
b11111111100 !
b11111111100 '
b1111000 (
1"
#1250000
0"
#1275000
b0 !
b0 '
b1111000 (
1"
#1300000
0"
#1325000
b101 !
b101 '
b1111000 (
1"
#1350000
0"
#1375000
b1000 !
b1000 '
b1111000 (
1"
#1400000
0"
#1425000
b1100 !
b1100 '
b1111000 (
1"
#1450000
0"
#1475000
b1110 !
b1110 '
b1111000 (
1"
#1500000
0"
#1525000
b10000 !
b10000 '
b1111000 (
1"
#1550000
0"
#1575000
b1111000 (
1"
#1600000
0"
#1625000
b1111 !
b1111 '
b1111000 (
1"
#1650000
0"
#1675000
b1100 !
b1100 '
b1111000 (
1"
#1700000
0"
#1725000
b1000 !
b1000 '
b1111000 (
1"
#1750000
0"
#1775000
b11 !
b11 '
b1111000 (
1"
#1800000
0"
#1825000
b11111111101 !
b11111111101 '
b1111000 (
1"
#1850000
0"
#1875000
b11111110110 !
b11111110110 '
b1111000 (
1"
#1900000
0"
#1925000
b11111101111 !
b11111101111 '
b1111000 (
1"
#1950000
0"
#1975000
b11111101000 !
b11111101000 '
b1111000 (
1"
#2000000
0"
#2025000
b11111100010 !
b11111100010 '
b1111000 (
1"
#2050000
0"
#2075000
b11111011110 !
b11111011110 '
b1111000 (
1"
#2100000
0"
#2125000
b11111011011 !
b11111011011 '
b1111000 (
1"
#2150000
0"
#2175000
b11111011010 !
b11111011010 '
b1111000 (
1"
#2200000
0"
#2225000
b11111011100 !
b11111011100 '
b1111000 (
1"
#2250000
0"
#2275000
b11111100001 !
b11111100001 '
b1111000 (
1"
#2300000
0"
#2325000
b11111101001 !
b11111101001 '
b1111000 (
1"
#2350000
0"
#2375000
b11111110100 !
b11111110100 '
b1111000 (
1"
#2400000
0"
#2425000
b10 !
b10 '
b1111000 (
1"
#2450000
0"
#2475000
b10010 !
b10010 '
b1111000 (
1"
#2500000
0"
#2525000
b100101 !
b100101 '
b1111000 (
1"
#2550000
0"
#2575000
b111000 !
b111000 '
b1111000 (
1"
#2600000
0"
#2625000
b1001100 !
b1001100 '
b1111000 (
1"
#2650000
0"
#2675000
b1100000 !
b1100000 '
b1111000 (
1"
#2700000
0"
#2725000
b1110011 !
b1110011 '
b1111000 (
1"
#2750000
0"
#2775000
b10000100 !
b10000100 '
b1111000 (
1"
#2800000
0"
#2825000
b10010011 !
b10010011 '
b1111000 (
1"
#2850000
0"
#2875000
b10011111 !
b10011111 '
b1111000 (
1"
#2900000
0"
#2925000
b10100111 !
b10100111 '
b1111000 (
1"
#2950000
0"
#2975000
b10101011 !
b10101011 '
b1111000 (
1"
#3000000
0"
#3025000
b1111000 (
1"
#3050000
0"
#3075000
b10100111 !
b10100111 '
b1111000 (
1"
#3100000
0"
#3125000
b10011111 !
b10011111 '
b1111000 (
1"
#3150000
0"
#3175000
b10010011 !
b10010011 '
b1111000 (
1"
#3200000
0"
#3225000
b10000100 !
b10000100 '
b1111000 (
1"
#3250000
0"
#3275000
b1110011 !
b1110011 '
b1111000 (
1"
#3300000
0"
#3325000
b1100000 !
b1100000 '
b1111000 (
1"
#3350000
0"
#3375000
b1001100 !
b1001100 '
b1111000 (
1"
#3400000
0"
#3425000
b111000 !
b111000 '
b1111000 (
1"
#3450000
0"
#3475000
b100101 !
b100101 '
b1111000 (
1"
#3500000
0"
#3525000
b10010 !
b10010 '
b1111000 (
1"
#3550000
0"
#3575000
b10 !
b10 '
b1111000 (
1"
#3600000
0"
#3625000
b11111110100 !
b11111110100 '
b1111000 (
1"
#3650000
0"
#3675000
b11111101001 !
b11111101001 '
b1111000 (
1"
#3700000
0"
#3725000
b11111100001 !
b11111100001 '
b1111000 (
1"
#3750000
0"
#3775000
b11111011100 !
b11111011100 '
b1111000 (
1"
#3800000
0"
#3825000
b11111011010 !
b11111011010 '
b1111000 (
1"
#3850000
0"
#3875000
b11111011011 !
b11111011011 '
b1111000 (
1"
#3900000
0"
#3925000
b11111011110 !
b11111011110 '
b1111000 (
1"
#3950000
0"
#3975000
b11111100010 !
b11111100010 '
b1111000 (
1"
#4000000
0"
#4025000
b11111101000 !
b11111101000 '
b1111000 (
1"
#4050000
0"
#4075000
b11111101111 !
b11111101111 '
b1111000 (
1"
#4100000
0"
#4125000
b11111110110 !
b11111110110 '
b1111000 (
1"
#4150000
0"
#4175000
b11111111101 !
b11111111101 '
b1111000 (
1"
#4200000
0"
#4225000
b11 !
b11 '
b1111000 (
1"
#4250000
0"
#4275000
b1000 !
b1000 '
b1111000 (
1"
#4300000
0"
#4325000
b1100 !
b1100 '
b1111000 (
1"
#4350000
0"
#4375000
b1111 !
b1111 '
b1111000 (
1"
#4400000
0"
#4425000
b10000 !
b10000 '
b1111000 (
1"
#4450000
0"
#4475000
b1111000 (
1"
#4500000
0"
#4525000
b1110 !
b1110 '
b1111000 (
1"
#4550000
0"
#4575000
b1100 !
b1100 '
b1111000 (
1"
#4600000
0"
#4625000
b1000 !
b1000 '
b1111000 (
1"
#4650000
0"
#4675000
b101 !
b101 '
b1111000 (
1"
#4700000
0"
#4725000
b0 !
b0 '
b1111000 (
1"
#4750000
0"
#4775000
b11111111100 !
b11111111100 '
b1111000 (
1"
#4800000
0"
#4825000
b11111111001 !
b11111111001 '
b1111000 (
1"
#4850000
0"
#4875000
b11111110110 !
b11111110110 '
b1111000 (
1"
#4900000
0"
#4925000
b11111110011 !
b11111110011 '
b1111000 (
1"
#4950000
0"
#4975000
b11111110010 !
b11111110010 '
b1111000 (
1"
#5000000
0"
#5025000
b11111110001 !
b11111110001 '
b1111000 (
1"
#5050000
0"
#5075000
b1111000 (
1"
#5100000
0"
#5125000
b11111110010 !
b11111110010 '
b1111000 (
1"
#5150000
0"
#5175000
b11111110100 !
b11111110100 '
b1111000 (
1"
#5200000
0"
#5225000
b11111110110 !
b11111110110 '
b1111000 (
1"
#5250000
0"
#5275000
b11111111000 !
b11111111000 '
b1111000 (
1"
#5300000
0"
#5325000
b11111111011 !
b11111111011 '
b1111000 (
1"
#5350000
0"
#5375000
b11111111101 !
b11111111101 '
b1111000 (
1"
#5400000
0"
#5425000
b0 !
b0 '
b1111000 (
1"
#5450000
0"
#5475000
b10 !
b10 '
b1111000 (
1"
#5500000
0"
#5525000
b100 !
b100 '
b1111000 (
1"
#5550000
0"
#5575000
b110 !
b110 '
b1111000 (
1"
#5600000
0"
#5625000
b111 !
b111 '
b1111000 (
1"
#5650000
0"
#5675000
b1111000 (
1"
#5700000
0"
#5725000
b1111000 (
1"
#5750000
0"
#5775000
b1111000 (
1"
#5800000
0"
#5825000
b110 !
b110 '
b1111000 (
1"
#5850000
0"
#5875000
b101 !
b101 '
b1111000 (
1"
#5900000
0"
#5925000
b100 !
b100 '
b1111000 (
1"
#5950000
0"
#5975000
b1001 !
b1001 '
b1111000 (
1"
#6000000
0"
#6025000
b0 !
b0 '
b1111000 (
1"
#6050000
0"
#6075000
b1111000 (
1"
#6100000
0"
#6125000
b1111000 (
1"
#6150000
0"
#6175000
b1111000 (
1"
#6200000
0"
#6225000
b1111000 (
1"
#6250000
0"
#6275000
b1111000 (
1"
#6300000
0"
#6325000
b1111000 (
1"
#6350000
0"
#6375000
b1111000 (
1"
#6400000
0"
#6425000
b1111000 (
1"
#6450000
0"
#6475000
b1111000 (
1"
#6500000
0"
#6525000
b1111000 (
1"
#6550000
0"
#6575000
b1111000 (
1"
#6600000
0"
#6625000
b1111000 (
1"
#6650000
0"
#6675000
b1111000 (
1"
#6700000
0"
#6725000
b1111000 (
1"
#6750000
0"
#6775000
b1111000 (
1"
#6800000
0"
#6825000
b1111000 (
1"
#6850000
0"
#6875000
b1111000 (
1"
#6900000
0"
#6925000
b1111000 (
1"
#6950000
0"
#6975000
b1111000 (
1"
#7000000
0"
#7025000
b1111000 (
1"
#7050000
0"
#7075000
b1111000 (
1"
#7100000
0"
#7125000
b1111000 (
1"
#7150000
0"
#7175000
b1111000 (
1"
#7200000
0"
#7225000
b1111000 (
1"
#7250000
0"
#7275000
b1111000 (
1"
#7300000
0"
#7325000
b1111000 (
1"
#7350000
0"
#7375000
b1111000 (
1"
#7400000
0"
#7425000
b1111000 (
1"
#7450000
0"
#7475000
b1111000 (
1"
#7500000
0"
#7525000
b1111000 (
1"
#7550000
0"
#7575000
b1111000 (
1"
#7600000
0"
#7625000
b1111000 (
1"
#7650000
0"
#7675000
b1111000 (
1"
#7700000
0"
#7725000
b1111000 (
1"
#7750000
0"
#7775000
b1111000 (
1"
#7800000
0"
#7825000
b1111000 (
1"
#7850000
0"
#7875000
b1111000 (
1"
#7900000
0"
#7925000
b1111000 (
1"
#7950000
0"
#7975000
b1111000 (
1"
#8000000
0"
#8025000
b1111000 (
1"
#8050000
0"
#8075000
b1111000 (
1"
#8100000
0"
#8125000
b1111000 (
1"
#8150000
0"
#8175000
b1111000 (
1"
#8200000
0"
#8225000
b1111000 (
1"
#8250000
0"
#8275000
b1111000 (
1"
#8300000
0"
#8325000
b1111000 (
1"
#8350000
0"
#8375000
b1111000 (
1"
#8400000
0"
#8425000
b1111000 (
1"
#8450000
0"
#8475000
b1111000 (
1"
#8500000
0"
#8525000
b1111000 (
1"
#8550000
0"
#8575000
b1111000 (
1"
#8600000
0"
#8625000
b1111000 (
1"
#8650000
0"
#8675000
b1111000 (
1"
#8700000
0"
#8725000
b1111000 (
1"
#8750000
0"
#8775000
b1111000 (
1"
#8800000
0"
#8825000
b1111000 (
1"
#8850000
0"
#8875000
b1111000 (
1"
#8900000
0"
#8925000
b1111000 (
1"
#8950000
0"
#8975000
b1111000 (
1"
#9000000
0"
#9025000
b1111000 (
1"
#9050000
0"
#9075000
b1111000 (
1"
#9100000
0"
#9125000
b1111000 (
1"
#9150000
0"
#9175000
b1111000 (
1"
#9200000
0"
#9225000
b1111000 (
1"
#9250000
0"
#9275000
b1111000 (
1"
#9300000
0"
#9325000
b1111000 (
1"
#9350000
0"
#9375000
b1111000 (
1"
#9400000
0"
#9425000
b1111000 (
1"
#9450000
0"
#9475000
b1111000 (
1"
#9500000
0"
#9525000
b1111000 (
1"
#9550000
0"
#9575000
b1111000 (
1"
#9600000
0"
#9625000
b1111000 (
1"
#9650000
0"
#9675000
b1111000 (
1"
#9700000
0"
#9725000
b1111000 (
1"
#9750000
0"
#9775000
b1111000 (
1"
#9800000
0"
#9825000
b1111000 (
1"
#9850000
0"
#9875000
b1111000 (
1"
#9900000
0"
#9925000
b1111000 (
1"
#9950000
0"
#9975000
b1111000 (
1"
#10000000
0"
#10025000
b1111000 (
1"
